[{"clip":"AF003_1992_EP_SU2011_AD_03","tag":"Prep","type":"Gram","end":"tt-284","start":"tt-284"},{"clip":"AF003_1992_EP_SU2011_AD_03","tag":"Imperf","type":"Gram","end":"tt-286","start":"tt-286"},{"clip":"AF003_1992_EP_SU2011_AD_03","tag":"Pron","type":"Gram","end":"tt-294","start":"tt-294"},{"clip":"AF003_1992_EP_SU2011_AD_03","tag":"Pron:Sujeto","type":"Gram","end":"tt-294","start":"tt-294"},{"clip":"AF003_1992_EP_SU2011_AD_03","tag":"Indefinido","type":"Gram","end":"tt-299","start":"tt-299"},{"clip":"AF003_1992_EP_SU2011_AD_03","tag":"Prep","type":"Gram","end":"tt-300","start":"tt-300"},{"clip":"AF003_1992_EP_SU2011_AD_03","tag":"Prep","type":"Gram","end":"tt-303","start":"tt-303"},{"clip":"AF003_1992_EP_SU2011_AD_03","tag":"Prep","type":"Gram","end":"tt-305","start":"tt-305"},{"clip":"AF003_1992_EP_SU2011_AD_03","tag":"Indefinido","type":"Gram","end":"tt-314","start":"tt-314"},{"clip":"AF003_1992_EP_SU2011_AD_03","tag":"Det","type":"Gram","end":"tt-315","start":"tt-315"},{"clip":"AF003_1992_EP_SU2011_AD_03","tag":"Det:Art","type":"Gram","end":"tt-315","start":"tt-315"},{"clip":"AF003_1992_EP_SU2011_AD_03","tag":"Indefinido","type":"Gram","end":"tt-318","start":"tt-318"},{"clip":"AF003_1992_EP_SU2011_AD_03","tag":"Prep","type":"Gram","end":"tt-319","start":"tt-319"},{"clip":"AF003_1992_EP_SU2011_AD_03","tag":"Prep","type":"Gram","end":"tt-323","start":"tt-323"},{"clip":"AF003_1992_EP_SU2011_AD_03","tag":"Indefinido","type":"Gram","end":"tt-331","start":"tt-331"},{"clip":"AF003_1992_EP_SU2011_AD_03","tag":"RecuDiscurso","type":"Prag","end":"tt-333","start":"tt-333"},{"clip":"AF003_1992_EP_SU2011_AD_03","tag":"RecuDiscurso:GanarTiempo","type":"Prag","end":"tt-333","start":"tt-333"},{"clip":"AF003_1992_EP_SU2011_AD_03","tag":"Prep","type":"Gram","end":"tt-342","start":"tt-342"},{"clip":"AF003_1992_EP_SU2011_AD_03","tag":"Det","type":"Gram","end":"tt-343","start":"tt-343"},{"clip":"AF003_1992_EP_SU2011_AD_03","tag":"Det:Art","type":"Gram","end":"tt-343","start":"tt-343"},{"clip":"AF003_1992_EP_SU2011_AD_03","tag":"Indefinido","type":"Gram","end":"tt-348","start":"tt-348"},{"clip":"AF003_1992_EP_SU2011_AD_03","tag":"Fraseol","type":"Vocab","end":"tt-319","start":"tt-318"},{"clip":"AF003_1992_EP_SU2011_AD_03","tag":"Fraseol:VerbPrep","type":"Vocab","end":"tt-319","start":"tt-318"},{"clip":"AF003_1992_EP_SU2011_AD_03","tag":"Noun:administración","type":"Vocab","end":"tt-304","start":"tt-304"},{"clip":"AF003_1992_EP_SU2011_AD_03","tag":"Verb:trabajar","type":"Vocab","end":"tt-349","start":"tt-349"},{"clip":"AF003_1992_EP_SU2011_AD_03","tag":"Noun:papá","type":"Vocab","end":"tt-347","start":"tt-347"},{"clip":"AF003_1992_EP_SU2011_AD_03","tag":"Noun:UNK","type":"Vocab","end":"tt-287","start":"tt-287"},{"clip":"AF003_1992_EP_SU2011_AD_03","tag":"Verb:graduar","type":"Vocab","end":"tt-299","start":"tt-299"},{"clip":"AF003_1992_EP_SU2011_AD_03","tag":"Noun:mamá","type":"Vocab","end":"tt-293","start":"tt-293"},{"clip":"AF003_1992_EP_SU2011_AD_03","tag":"Noun:padre","type":"Vocab","end":"tt-288","start":"tt-288"},{"clip":"AF003_1992_EP_SU2011_AD_03","tag":"Noun:construcción","type":"Vocab","end":"tt-324","start":"tt-324"},{"clip":"AF003_1992_EP_SU2011_AD_03","tag":"Verb:hacer","type":"Vocab","end":"tt-340","start":"tt-340"},{"clip":"AF003_1992_EP_SU2011_AD_03","tag":"Verb:seguir","type":"Vocab","end":"tt-348","start":"tt-348"},{"clip":"AF003_1992_EP_SU2011_AD_03","tag":"Noun:empresa","type":"Vocab","end":"tt-306","start":"tt-306"},{"clip":"AF003_1992_EP_SU2011_AD_03","tag":"Noun:este","type":"Vocab","end":"tt-321","start":"tt-321"},{"clip":"AF003_1992_EP_SU2011_AD_03","tag":"Verb:terminar","type":"Vocab","end":"tt-314","start":"tt-314"},{"clip":"AF003_1992_EP_SU2011_AD_03","tag":"Noun:este","type":"Vocab","end":"tt-312","start":"tt-312"},{"clip":"AF003_1992_EP_SU2011_AD_03","tag":"Noun:trabajo","type":"Vocab","end":"tt-285","start":"tt-285"},{"clip":"AF003_1992_EP_SU2011_AD_03","tag":"Noun:casa","type":"Vocab","end":"tt-344","start":"tt-344"},{"clip":"AF003_1992_EP_SU2011_AD_03","tag":"Noun:escuela","type":"Vocab","end":"tt-316","start":"tt-316"},{"clip":"AF003_1992_EP_SU2011_AD_03","tag":"Noun:mamá","type":"Vocab","end":"tt-336","start":"tt-336"},{"clip":"AF003_1992_EP_SU2011_AD_03","tag":"Verb:hacer","type":"Vocab","end":"tt-286","start":"tt-286"},{"clip":"AF003_1992_EP_SU2011_AD_03","tag":"Noun:tipo","type":"Vocab","end":"tt-283","start":"tt-283"},{"clip":"AF003_1992_EP_SU2011_AD_03","tag":"Noun:licenciatura","type":"Vocab","end":"tt-302","start":"tt-302"},{"clip":"AF003_1992_EP_SU2011_AD_03","tag":"Noun:papá","type":"Vocab","end":"tt-309","start":"tt-309"},{"clip":"AF003_1992_EP_SU2011_AD_03","tag":"Verb:trabajar","type":"Vocab","end":"tt-320","start":"tt-320"},{"clip":"AF003_1992_EP_SU2011_AD_03","tag":"Verb:casar","type":"Vocab","end":"tt-331","start":"tt-331"},{"clip":"AF003_1992_EP_SU2011_AD_03","tag":"Noun:cargo","type":"Vocab","end":"tt-341","start":"tt-341"},{"clip":"AF003_1992_EP_SU2011_AD_03","tag":"Noun:este","type":"Vocab","end":"tt-296","start":"tt-296"}]