[{"clip":"MF019_1971_CT_SU2011_VA_04","tag":"Indefinido","type":"Gram","end":"tt-1042","start":"tt-1042"},{"clip":"MF019_1971_CT_SU2011_VA_04","tag":"Prep","type":"Gram","end":"tt-1043","start":"tt-1043"},{"clip":"MF019_1971_CT_SU2011_VA_04","tag":"Det","type":"Gram","end":"tt-1052","start":"tt-1052"},{"clip":"MF019_1971_CT_SU2011_VA_04","tag":"Det:Pos","type":"Gram","end":"tt-1052","start":"tt-1052"},{"clip":"MF019_1971_CT_SU2011_VA_04","tag":"Pron","type":"Gram","end":"tt-1055","start":"tt-1055"},{"clip":"MF019_1971_CT_SU2011_VA_04","tag":"Pron:Sujeto","type":"Gram","end":"tt-1055","start":"tt-1055"},{"clip":"MF019_1971_CT_SU2011_VA_04","tag":"Indefinido","type":"Gram","end":"tt-1056","start":"tt-1056"},{"clip":"MF019_1971_CT_SU2011_VA_04","tag":"Det","type":"Gram","end":"tt-1057","start":"tt-1057"},{"clip":"MF019_1971_CT_SU2011_VA_04","tag":"Det:Art","type":"Gram","end":"tt-1057","start":"tt-1057"},{"clip":"MF019_1971_CT_SU2011_VA_04","tag":"Pron","type":"Gram","end":"tt-1062","start":"tt-1062"},{"clip":"MF019_1971_CT_SU2011_VA_04","tag":"Pron:Objeto","type":"Gram","end":"tt-1062","start":"tt-1062"},{"clip":"MF019_1971_CT_SU2011_VA_04","tag":"MarcadoresDisc","type":"Prag","end":"tt-1066","start":"tt-1066"},{"clip":"MF019_1971_CT_SU2011_VA_04","tag":"MarcadoresDisc:Revision","type":"Prag","end":"tt-1066","start":"tt-1066"},{"clip":"MF019_1971_CT_SU2011_VA_04","tag":"Det","type":"Gram","end":"tt-1067","start":"tt-1067"},{"clip":"MF019_1971_CT_SU2011_VA_04","tag":"Det:Art","type":"Gram","end":"tt-1067","start":"tt-1067"},{"clip":"MF019_1971_CT_SU2011_VA_04","tag":"Imperf","type":"Gram","end":"tt-1069","start":"tt-1069"},{"clip":"MF019_1971_CT_SU2011_VA_04","tag":"Pron","type":"Gram","end":"tt-1073","start":"tt-1073"},{"clip":"MF019_1971_CT_SU2011_VA_04","tag":"Pron:Sujeto","type":"Gram","end":"tt-1073","start":"tt-1073"},{"clip":"MF019_1971_CT_SU2011_VA_04","tag":"Indefinido","type":"Gram","end":"tt-1074","start":"tt-1074"},{"clip":"MF019_1971_CT_SU2011_VA_04","tag":"Det","type":"Gram","end":"tt-1077","start":"tt-1077"},{"clip":"MF019_1971_CT_SU2011_VA_04","tag":"Det:Art","type":"Gram","end":"tt-1077","start":"tt-1077"},{"clip":"MF019_1971_CT_SU2011_VA_04","tag":"Prep","type":"Gram","end":"tt-1079","start":"tt-1079"},{"clip":"MF019_1971_CT_SU2011_VA_04","tag":"Pron","type":"Gram","end":"tt-1082","start":"tt-1082"},{"clip":"MF019_1971_CT_SU2011_VA_04","tag":"Pron:Sujeto","type":"Gram","end":"tt-1082","start":"tt-1082"},{"clip":"MF019_1971_CT_SU2011_VA_04","tag":"Imperf","type":"Gram","end":"tt-1083","start":"tt-1083"},{"clip":"MF019_1971_CT_SU2011_VA_04","tag":"Det","type":"Gram","end":"tt-1086","start":"tt-1086"},{"clip":"MF019_1971_CT_SU2011_VA_04","tag":"Det:Pos","type":"Gram","end":"tt-1086","start":"tt-1086"},{"clip":"MF019_1971_CT_SU2011_VA_04","tag":"MarcadoresDisc","type":"Prag","end":"tt-1088","start":"tt-1088"},{"clip":"MF019_1971_CT_SU2011_VA_04","tag":"MarcadoresDisc:Revision","type":"Prag","end":"tt-1088","start":"tt-1088"},{"clip":"MF019_1971_CT_SU2011_VA_04","tag":"Pron","type":"Gram","end":"tt-1090","start":"tt-1090"},{"clip":"MF019_1971_CT_SU2011_VA_04","tag":"Pron:Objeto","type":"Gram","end":"tt-1090","start":"tt-1090"},{"clip":"MF019_1971_CT_SU2011_VA_04","tag":"Imperf","type":"Gram","end":"tt-1091","start":"tt-1091"},{"clip":"MF019_1971_CT_SU2011_VA_04","tag":"SerEstar","type":"Gram","end":"tt-1091","start":"tt-1091"},{"clip":"MF019_1971_CT_SU2011_VA_04","tag":"SerEstar:Ser","type":"Gram","end":"tt-1091","start":"tt-1091"},{"clip":"MF019_1971_CT_SU2011_VA_04","tag":"Det","type":"Gram","end":"tt-1094","start":"tt-1094"},{"clip":"MF019_1971_CT_SU2011_VA_04","tag":"Det:Art","type":"Gram","end":"tt-1094","start":"tt-1094"},{"clip":"MF019_1971_CT_SU2011_VA_04","tag":"Imperf","type":"Gram","end":"tt-1096","start":"tt-1096"},{"clip":"MF019_1971_CT_SU2011_VA_04","tag":"Det","type":"Gram","end":"tt-1099","start":"tt-1099"},{"clip":"MF019_1971_CT_SU2011_VA_04","tag":"Det:Art","type":"Gram","end":"tt-1099","start":"tt-1099"},{"clip":"MF019_1971_CT_SU2011_VA_04","tag":"Imperf","type":"Gram","end":"tt-1102","start":"tt-1102"},{"clip":"MF019_1971_CT_SU2011_VA_04","tag":"Det","type":"Gram","end":"tt-1107","start":"tt-1107"},{"clip":"MF019_1971_CT_SU2011_VA_04","tag":"Det:Pos","type":"Gram","end":"tt-1107","start":"tt-1107"},{"clip":"MF019_1971_CT_SU2011_VA_04","tag":"Imperf","type":"Gram","end":"tt-1109","start":"tt-1109"},{"clip":"MF019_1971_CT_SU2011_VA_04","tag":"Pron","type":"Gram","end":"tt-1113","start":"tt-1113"},{"clip":"MF019_1971_CT_SU2011_VA_04","tag":"Pron:Sujeto","type":"Gram","end":"tt-1113","start":"tt-1113"},{"clip":"MF019_1971_CT_SU2011_VA_04","tag":"Indefinido","type":"Gram","end":"tt-1114","start":"tt-1114"},{"clip":"MF019_1971_CT_SU2011_VA_04","tag":"Haber","type":"Gram","end":"tt-1118","start":"tt-1118"},{"clip":"MF019_1971_CT_SU2011_VA_04","tag":"Haber:Exist","type":"Gram","end":"tt-1118","start":"tt-1118"},{"clip":"MF019_1971_CT_SU2011_VA_04","tag":"Prep","type":"Gram","end":"tt-1123","start":"tt-1123"},{"clip":"MF019_1971_CT_SU2011_VA_04","tag":"Prep","type":"Gram","end":"tt-1125","start":"tt-1125"},{"clip":"MF019_1971_CT_SU2011_VA_04","tag":"Det","type":"Gram","end":"tt-1126","start":"tt-1126"},{"clip":"MF019_1971_CT_SU2011_VA_04","tag":"Det:Art","type":"Gram","end":"tt-1126","start":"tt-1126"},{"clip":"MF019_1971_CT_SU2011_VA_04","tag":"Haber","type":"Gram","end":"tt-1129","start":"tt-1129"},{"clip":"MF019_1971_CT_SU2011_VA_04","tag":"Haber:Exist","type":"Gram","end":"tt-1129","start":"tt-1129"},{"clip":"MF019_1971_CT_SU2011_VA_04","tag":"Indefinido","type":"Gram","end":"tt-1133","start":"tt-1133"},{"clip":"MF019_1971_CT_SU2011_VA_04","tag":"Det","type":"Gram","end":"tt-1134","start":"tt-1134"},{"clip":"MF019_1971_CT_SU2011_VA_04","tag":"Det:Pos","type":"Gram","end":"tt-1134","start":"tt-1134"},{"clip":"MF019_1971_CT_SU2011_VA_04","tag":"Prep","type":"Gram","end":"tt-1139","start":"tt-1139"},{"clip":"MF019_1971_CT_SU2011_VA_04","tag":"Prep","type":"Gram","end":"tt-1140","start":"tt-1140"},{"clip":"MF019_1971_CT_SU2011_VA_04","tag":"Prep","type":"Gram","end":"tt-1143","start":"tt-1143"},{"clip":"MF019_1971_CT_SU2011_VA_04","tag":"Det","type":"Gram","end":"tt-1146","start":"tt-1146"},{"clip":"MF019_1971_CT_SU2011_VA_04","tag":"Det:Art","type":"Gram","end":"tt-1146","start":"tt-1146"},{"clip":"MF019_1971_CT_SU2011_VA_04","tag":"Prep","type":"Gram","end":"tt-1152","start":"tt-1152"},{"clip":"MF019_1971_CT_SU2011_VA_04","tag":"MarcadoresDisc","type":"Prag","end":"tt-1155","start":"tt-1155"},{"clip":"MF019_1971_CT_SU2011_VA_04","tag":"MarcadoresDisc:Revision","type":"Prag","end":"tt-1155","start":"tt-1155"},{"clip":"MF019_1971_CT_SU2011_VA_04","tag":"Det","type":"Gram","end":"tt-1157","start":"tt-1157"},{"clip":"MF019_1971_CT_SU2011_VA_04","tag":"Det:Pos","type":"Gram","end":"tt-1157","start":"tt-1157"},{"clip":"MF019_1971_CT_SU2011_VA_04","tag":"Imperf","type":"Gram","end":"tt-1159","start":"tt-1159"},{"clip":"MF019_1971_CT_SU2011_VA_04","tag":"Det","type":"Gram","end":"tt-1165","start":"tt-1165"},{"clip":"MF019_1971_CT_SU2011_VA_04","tag":"Det:Art","type":"Gram","end":"tt-1165","start":"tt-1165"},{"clip":"MF019_1971_CT_SU2011_VA_04","tag":"Det","type":"Gram","end":"tt-1167","start":"tt-1167"},{"clip":"MF019_1971_CT_SU2011_VA_04","tag":"Det:Art","type":"Gram","end":"tt-1167","start":"tt-1167"},{"clip":"MF019_1971_CT_SU2011_VA_04","tag":"Imperf","type":"Gram","end":"tt-1174","start":"tt-1174"},{"clip":"MF019_1971_CT_SU2011_VA_04","tag":"SerEstar","type":"Gram","end":"tt-1174","start":"tt-1174"},{"clip":"MF019_1971_CT_SU2011_VA_04","tag":"SerEstar:Ser","type":"Gram","end":"tt-1174","start":"tt-1174"},{"clip":"MF019_1971_CT_SU2011_VA_04","tag":"Det","type":"Gram","end":"tt-1181","start":"tt-1181"},{"clip":"MF019_1971_CT_SU2011_VA_04","tag":"Det:Art","type":"Gram","end":"tt-1181","start":"tt-1181"},{"clip":"MF019_1971_CT_SU2011_VA_04","tag":"SerEstar","type":"Gram","end":"tt-1183","start":"tt-1183"},{"clip":"MF019_1971_CT_SU2011_VA_04","tag":"SerEstar:Ser","type":"Gram","end":"tt-1183","start":"tt-1183"},{"clip":"MF019_1971_CT_SU2011_VA_04","tag":"Det","type":"Gram","end":"tt-1187","start":"tt-1187"},{"clip":"MF019_1971_CT_SU2011_VA_04","tag":"Det:Pos","type":"Gram","end":"tt-1187","start":"tt-1187"},{"clip":"MF019_1971_CT_SU2011_VA_04","tag":"SerEstar","type":"Gram","end":"tt-1197","start":"tt-1197"},{"clip":"MF019_1971_CT_SU2011_VA_04","tag":"SerEstar:Ser","type":"Gram","end":"tt-1197","start":"tt-1197"},{"clip":"MF019_1971_CT_SU2011_VA_04","tag":"Prep","type":"Gram","end":"tt-1199","start":"tt-1199"},{"clip":"MF019_1971_CT_SU2011_VA_04","tag":"SerEstar","type":"Gram","end":"tt-1212","start":"tt-1212"},{"clip":"MF019_1971_CT_SU2011_VA_04","tag":"SerEstar:Ser","type":"Gram","end":"tt-1212","start":"tt-1212"},{"clip":"MF019_1971_CT_SU2011_VA_04","tag":"MarcadoresDisc","type":"Prag","end":"tt-1217","start":"tt-1217"},{"clip":"MF019_1971_CT_SU2011_VA_04","tag":"MarcadoresDisc:Revision","type":"Prag","end":"tt-1217","start":"tt-1217"},{"clip":"MF019_1971_CT_SU2011_VA_04","tag":"SerEstar","type":"Gram","end":"tt-1218","start":"tt-1218"},{"clip":"MF019_1971_CT_SU2011_VA_04","tag":"SerEstar:Ser","type":"Gram","end":"tt-1218","start":"tt-1218"},{"clip":"MF019_1971_CT_SU2011_VA_04","tag":"Det","type":"Gram","end":"tt-1219","start":"tt-1219"},{"clip":"MF019_1971_CT_SU2011_VA_04","tag":"Det:Art","type":"Gram","end":"tt-1219","start":"tt-1219"},{"clip":"MF019_1971_CT_SU2011_VA_04","tag":"Prep","type":"Gram","end":"tt-1222","start":"tt-1222"},{"clip":"MF019_1971_CT_SU2011_VA_04","tag":"Prep","type":"Gram","end":"tt-1225","start":"tt-1225"},{"clip":"MF019_1971_CT_SU2011_VA_04","tag":"Prep","type":"Gram","end":"tt-1228","start":"tt-1228"},{"clip":"MF019_1971_CT_SU2011_VA_04","tag":"Pron","type":"Gram","end":"tt-1232","start":"tt-1232"},{"clip":"MF019_1971_CT_SU2011_VA_04","tag":"Pron:Sujeto","type":"Gram","end":"tt-1232","start":"tt-1232"},{"clip":"MF019_1971_CT_SU2011_VA_04","tag":"Pron","type":"Gram","end":"tt-1237","start":"tt-1237"},{"clip":"MF019_1971_CT_SU2011_VA_04","tag":"Pron:Sujeto","type":"Gram","end":"tt-1237","start":"tt-1237"},{"clip":"MF019_1971_CT_SU2011_VA_04","tag":"MSub","type":"Gram","end":"tt-1240","start":"tt-1240"},{"clip":"MF019_1971_CT_SU2011_VA_04","tag":"MSub:Pret","type":"Gram","end":"tt-1240","start":"tt-1240"},{"clip":"MF019_1971_CT_SU2011_VA_04","tag":"Det","type":"Gram","end":"tt-1241","start":"tt-1241"},{"clip":"MF019_1971_CT_SU2011_VA_04","tag":"Det:Art","type":"Gram","end":"tt-1241","start":"tt-1241"},{"clip":"MF019_1971_CT_SU2011_VA_04","tag":"Prep","type":"Gram","end":"tt-1243","start":"tt-1243"},{"clip":"MF019_1971_CT_SU2011_VA_04","tag":"Pron","type":"Gram","end":"tt-1247","start":"tt-1247"},{"clip":"MF019_1971_CT_SU2011_VA_04","tag":"Pron:Objeto","type":"Gram","end":"tt-1247","start":"tt-1247"},{"clip":"MF019_1971_CT_SU2011_VA_04","tag":"Imperf","type":"Gram","end":"tt-1248","start":"tt-1248"},{"clip":"MF019_1971_CT_SU2011_VA_04","tag":"Prep","type":"Gram","end":"tt-1251","start":"tt-1251"},{"clip":"MF019_1971_CT_SU2011_VA_04","tag":"MarcadoresDisc","type":"Prag","end":"tt-1253","start":"tt-1253"},{"clip":"MF019_1971_CT_SU2011_VA_04","tag":"MarcadoresDisc:Causa","type":"Prag","end":"tt-1253","start":"tt-1253"},{"clip":"MF019_1971_CT_SU2011_VA_04","tag":"Imperf","type":"Gram","end":"tt-1254","start":"tt-1254"},{"clip":"MF019_1971_CT_SU2011_VA_04","tag":"SerEstar","type":"Gram","end":"tt-1254","start":"tt-1254"},{"clip":"MF019_1971_CT_SU2011_VA_04","tag":"SerEstar:Ser","type":"Gram","end":"tt-1254","start":"tt-1254"},{"clip":"MF019_1971_CT_SU2011_VA_04","tag":"Det","type":"Gram","end":"tt-1255","start":"tt-1255"},{"clip":"MF019_1971_CT_SU2011_VA_04","tag":"Det:Art","type":"Gram","end":"tt-1255","start":"tt-1255"},{"clip":"MF019_1971_CT_SU2011_VA_04","tag":"MarcadoresDisc","type":"Prag","end":"tt-1259","start":"tt-1259"},{"clip":"MF019_1971_CT_SU2011_VA_04","tag":"MarcadoresDisc:Revision","type":"Prag","end":"tt-1259","start":"tt-1259"},{"clip":"MF019_1971_CT_SU2011_VA_04","tag":"Pron","type":"Gram","end":"tt-1262","start":"tt-1262"},{"clip":"MF019_1971_CT_SU2011_VA_04","tag":"Pron:Objeto","type":"Gram","end":"tt-1262","start":"tt-1262"},{"clip":"MF019_1971_CT_SU2011_VA_04","tag":"Imperf","type":"Gram","end":"tt-1263","start":"tt-1263"},{"clip":"MF019_1971_CT_SU2011_VA_04","tag":"Pron","type":"Gram","end":"tt-1272","start":"tt-1272"},{"clip":"MF019_1971_CT_SU2011_VA_04","tag":"Pron:Objeto","type":"Gram","end":"tt-1272","start":"tt-1272"},{"clip":"MF019_1971_CT_SU2011_VA_04","tag":"Imperf","type":"Gram","end":"tt-1273","start":"tt-1273"},{"clip":"MF019_1971_CT_SU2011_VA_04","tag":"SerEstar","type":"Gram","end":"tt-1279","start":"tt-1279"},{"clip":"MF019_1971_CT_SU2011_VA_04","tag":"SerEstar:Ser","type":"Gram","end":"tt-1279","start":"tt-1279"},{"clip":"MF019_1971_CT_SU2011_VA_04","tag":"SerEstar","type":"Gram","end":"tt-1282","start":"tt-1282"},{"clip":"MF019_1971_CT_SU2011_VA_04","tag":"SerEstar:Ser","type":"Gram","end":"tt-1282","start":"tt-1282"},{"clip":"MF019_1971_CT_SU2011_VA_04","tag":"MarcadoresDisc","type":"Prag","end":"tt-1285","start":"tt-1285"},{"clip":"MF019_1971_CT_SU2011_VA_04","tag":"MarcadoresDisc:Revision","type":"Prag","end":"tt-1285","start":"tt-1285"},{"clip":"MF019_1971_CT_SU2011_VA_04","tag":"Imperf","type":"Gram","end":"tt-1286","start":"tt-1286"},{"clip":"MF019_1971_CT_SU2011_VA_04","tag":"SerEstar","type":"Gram","end":"tt-1286","start":"tt-1286"},{"clip":"MF019_1971_CT_SU2011_VA_04","tag":"SerEstar:Ser","type":"Gram","end":"tt-1286","start":"tt-1286"},{"clip":"MF019_1971_CT_SU2011_VA_04","tag":"MSub","type":"Gram","end":"tt-1289","start":"tt-1289"},{"clip":"MF019_1971_CT_SU2011_VA_04","tag":"MSub:Pres","type":"Gram","end":"tt-1289","start":"tt-1289"},{"clip":"MF019_1971_CT_SU2011_VA_04","tag":"Haber","type":"Gram","end":"tt-1295","start":"tt-1295"},{"clip":"MF019_1971_CT_SU2011_VA_04","tag":"Haber:Exist","type":"Gram","end":"tt-1295","start":"tt-1295"},{"clip":"MF019_1971_CT_SU2011_VA_04","tag":"Prep","type":"Gram","end":"tt-1299","start":"tt-1299"},{"clip":"MF019_1971_CT_SU2011_VA_04","tag":"Det","type":"Gram","end":"tt-1300","start":"tt-1300"},{"clip":"MF019_1971_CT_SU2011_VA_04","tag":"Det:Art","type":"Gram","end":"tt-1300","start":"tt-1300"},{"clip":"MF019_1971_CT_SU2011_VA_04","tag":"Pron","type":"Gram","end":"tt-1302","start":"tt-1302"},{"clip":"MF019_1971_CT_SU2011_VA_04","tag":"Pron:Sujeto","type":"Gram","end":"tt-1302","start":"tt-1302"},{"clip":"MF019_1971_CT_SU2011_VA_04","tag":"Imperf","type":"Gram","end":"tt-1303","start":"tt-1303"},{"clip":"MF019_1971_CT_SU2011_VA_04","tag":"Imperf","type":"Gram","end":"tt-1309","start":"tt-1309"},{"clip":"MF019_1971_CT_SU2011_VA_04","tag":"Prep","type":"Gram","end":"tt-1314","start":"tt-1314"},{"clip":"MF019_1971_CT_SU2011_VA_04","tag":"SerEstar","type":"Gram","end":"tt-1323","start":"tt-1323"},{"clip":"MF019_1971_CT_SU2011_VA_04","tag":"SerEstar:Ser","type":"Gram","end":"tt-1323","start":"tt-1323"},{"clip":"MF019_1971_CT_SU2011_VA_04","tag":"Pron","type":"Gram","end":"tt-1328","start":"tt-1328"},{"clip":"MF019_1971_CT_SU2011_VA_04","tag":"Pron:Objeto","type":"Gram","end":"tt-1328","start":"tt-1328"},{"clip":"MF019_1971_CT_SU2011_VA_04","tag":"Imperf","type":"Gram","end":"tt-1329","start":"tt-1329"},{"clip":"MF019_1971_CT_SU2011_VA_04","tag":"Imperf","type":"Gram","end":"tt-1335","start":"tt-1335"},{"clip":"MF019_1971_CT_SU2011_VA_04","tag":"Imperf","type":"Gram","end":"tt-1339","start":"tt-1339"},{"clip":"MF019_1971_CT_SU2011_VA_04","tag":"Imperf","type":"Gram","end":"tt-1341","start":"tt-1341"},{"clip":"MF019_1971_CT_SU2011_VA_04","tag":"Imperf","type":"Gram","end":"tt-1346","start":"tt-1346"},{"clip":"MF019_1971_CT_SU2011_VA_04","tag":"SerEstar","type":"Gram","end":"tt-1346","start":"tt-1346"},{"clip":"MF019_1971_CT_SU2011_VA_04","tag":"SerEstar:Ser","type":"Gram","end":"tt-1346","start":"tt-1346"},{"clip":"MF019_1971_CT_SU2011_VA_04","tag":"Det","type":"Gram","end":"tt-1347","start":"tt-1347"},{"clip":"MF019_1971_CT_SU2011_VA_04","tag":"Det:Art","type":"Gram","end":"tt-1347","start":"tt-1347"},{"clip":"MF019_1971_CT_SU2011_VA_04","tag":"Imperf","type":"Gram","end":"tt-1349","start":"tt-1349"},{"clip":"MF019_1971_CT_SU2011_VA_04","tag":"SerEstar","type":"Gram","end":"tt-1349","start":"tt-1349"},{"clip":"MF019_1971_CT_SU2011_VA_04","tag":"SerEstar:Ser","type":"Gram","end":"tt-1349","start":"tt-1349"},{"clip":"MF019_1971_CT_SU2011_VA_04","tag":"Imperf","type":"Gram","end":"tt-1355","start":"tt-1355"},{"clip":"MF019_1971_CT_SU2011_VA_04","tag":"Det","type":"Gram","end":"tt-1356","start":"tt-1356"},{"clip":"MF019_1971_CT_SU2011_VA_04","tag":"Det:Art","type":"Gram","end":"tt-1356","start":"tt-1356"},{"clip":"MF019_1971_CT_SU2011_VA_04","tag":"Prep","type":"Gram","end":"tt-1359","start":"tt-1359"},{"clip":"MF019_1971_CT_SU2011_VA_04","tag":"Det","type":"Gram","end":"tt-1360","start":"tt-1360"},{"clip":"MF019_1971_CT_SU2011_VA_04","tag":"Det:Art","type":"Gram","end":"tt-1360","start":"tt-1360"},{"clip":"MF019_1971_CT_SU2011_VA_04","tag":"Imperf","type":"Gram","end":"tt-1373","start":"tt-1373"},{"clip":"MF019_1971_CT_SU2011_VA_04","tag":"Prep","type":"Gram","end":"tt-1374","start":"tt-1374"},{"clip":"MF019_1971_CT_SU2011_VA_04","tag":"Det","type":"Gram","end":"tt-1375","start":"tt-1375"},{"clip":"MF019_1971_CT_SU2011_VA_04","tag":"Det:Pos","type":"Gram","end":"tt-1375","start":"tt-1375"},{"clip":"MF019_1971_CT_SU2011_VA_04","tag":"MarcadoresDisc","type":"Prag","end":"tt-1378","start":"tt-1378"},{"clip":"MF019_1971_CT_SU2011_VA_04","tag":"MarcadoresDisc:Causa","type":"Prag","end":"tt-1378","start":"tt-1378"},{"clip":"MF019_1971_CT_SU2011_VA_04","tag":"Imperf","type":"Gram","end":"tt-1379","start":"tt-1379"},{"clip":"MF019_1971_CT_SU2011_VA_04","tag":"SerEstar","type":"Gram","end":"tt-1379","start":"tt-1379"},{"clip":"MF019_1971_CT_SU2011_VA_04","tag":"SerEstar:Ser","type":"Gram","end":"tt-1379","start":"tt-1379"},{"clip":"MF019_1971_CT_SU2011_VA_04","tag":"Det","type":"Gram","end":"tt-1380","start":"tt-1380"},{"clip":"MF019_1971_CT_SU2011_VA_04","tag":"Det:Art","type":"Gram","end":"tt-1380","start":"tt-1380"},{"clip":"MF019_1971_CT_SU2011_VA_04","tag":"Pron","type":"Gram","end":"tt-1384","start":"tt-1384"},{"clip":"MF019_1971_CT_SU2011_VA_04","tag":"Pron:Sujeto","type":"Gram","end":"tt-1384","start":"tt-1384"},{"clip":"MF019_1971_CT_SU2011_VA_04","tag":"Imperf","type":"Gram","end":"tt-1385","start":"tt-1385"},{"clip":"MF019_1971_CT_SU2011_VA_04","tag":"Pron","type":"Gram","end":"tt-1390","start":"tt-1390"},{"clip":"MF019_1971_CT_SU2011_VA_04","tag":"Pron:Sujeto","type":"Gram","end":"tt-1390","start":"tt-1390"},{"clip":"MF019_1971_CT_SU2011_VA_04","tag":"MSub","type":"Gram","end":"tt-1391","start":"tt-1391"},{"clip":"MF019_1971_CT_SU2011_VA_04","tag":"MSub:Pret","type":"Gram","end":"tt-1391","start":"tt-1391"},{"clip":"MF019_1971_CT_SU2011_VA_04","tag":"Imperf","type":"Gram","end":"tt-1400","start":"tt-1400"},{"clip":"MF019_1971_CT_SU2011_VA_04","tag":"SerEstar","type":"Gram","end":"tt-1400","start":"tt-1400"},{"clip":"MF019_1971_CT_SU2011_VA_04","tag":"SerEstar:Ser","type":"Gram","end":"tt-1400","start":"tt-1400"},{"clip":"MF019_1971_CT_SU2011_VA_04","tag":"Prep","type":"Gram","end":"tt-1402","start":"tt-1402"},{"clip":"MF019_1971_CT_SU2011_VA_04","tag":"Det","type":"Gram","end":"tt-1403","start":"tt-1403"},{"clip":"MF019_1971_CT_SU2011_VA_04","tag":"Det:Art","type":"Gram","end":"tt-1403","start":"tt-1403"},{"clip":"MF019_1971_CT_SU2011_VA_04","tag":"MarcadoresDisc","type":"Prag","end":"tt-1406","start":"tt-1406"},{"clip":"MF019_1971_CT_SU2011_VA_04","tag":"MarcadoresDisc:Causa","type":"Prag","end":"tt-1406","start":"tt-1406"},{"clip":"MF019_1971_CT_SU2011_VA_04","tag":"SerEstar","type":"Gram","end":"tt-1407","start":"tt-1407"},{"clip":"MF019_1971_CT_SU2011_VA_04","tag":"SerEstar:Ser","type":"Gram","end":"tt-1407","start":"tt-1407"},{"clip":"MF019_1971_CT_SU2011_VA_04","tag":"Pron","type":"Gram","end":"tt-1413","start":"tt-1413"},{"clip":"MF019_1971_CT_SU2011_VA_04","tag":"Pron:Objeto","type":"Gram","end":"tt-1413","start":"tt-1413"},{"clip":"MF019_1971_CT_SU2011_VA_04","tag":"Indefinido","type":"Gram","end":"tt-1414","start":"tt-1414"},{"clip":"MF019_1971_CT_SU2011_VA_04","tag":"Prep","type":"Gram","end":"tt-1415","start":"tt-1415"},{"clip":"MF019_1971_CT_SU2011_VA_04","tag":"Det","type":"Gram","end":"tt-1416","start":"tt-1416"},{"clip":"MF019_1971_CT_SU2011_VA_04","tag":"Det:Art","type":"Gram","end":"tt-1416","start":"tt-1416"},{"clip":"MF019_1971_CT_SU2011_VA_04","tag":"Pron","type":"Gram","end":"tt-1423","start":"tt-1423"},{"clip":"MF019_1971_CT_SU2011_VA_04","tag":"Pron:Sujeto","type":"Gram","end":"tt-1423","start":"tt-1423"},{"clip":"MF019_1971_CT_SU2011_VA_04","tag":"Imperf","type":"Gram","end":"tt-1424","start":"tt-1424"},{"clip":"MF019_1971_CT_SU2011_VA_04","tag":"Prep","type":"Gram","end":"tt-1426","start":"tt-1426"},{"clip":"MF019_1971_CT_SU2011_VA_04","tag":"Det","type":"Gram","end":"tt-1427","start":"tt-1427"},{"clip":"MF019_1971_CT_SU2011_VA_04","tag":"Det:Pos","type":"Gram","end":"tt-1427","start":"tt-1427"},{"clip":"MF019_1971_CT_SU2011_VA_04","tag":"Pron","type":"Gram","end":"tt-1430","start":"tt-1430"},{"clip":"MF019_1971_CT_SU2011_VA_04","tag":"Pron:Objeto","type":"Gram","end":"tt-1430","start":"tt-1430"},{"clip":"MF019_1971_CT_SU2011_VA_04","tag":"Imperf","type":"Gram","end":"tt-1431","start":"tt-1431"},{"clip":"MF019_1971_CT_SU2011_VA_04","tag":"Haber","type":"Gram","end":"tt-1434","start":"tt-1434"},{"clip":"MF019_1971_CT_SU2011_VA_04","tag":"Haber:Exist","type":"Gram","end":"tt-1434","start":"tt-1434"},{"clip":"MF019_1971_CT_SU2011_VA_04","tag":"Haber","type":"Gram","end":"tt-1437","start":"tt-1437"},{"clip":"MF019_1971_CT_SU2011_VA_04","tag":"Haber:Exist","type":"Gram","end":"tt-1437","start":"tt-1437"},{"clip":"MF019_1971_CT_SU2011_VA_04","tag":"MarcadoresDisc","type":"Prag","end":"tt-1439","start":"tt-1439"},{"clip":"MF019_1971_CT_SU2011_VA_04","tag":"MarcadoresDisc:Causa","type":"Prag","end":"tt-1439","start":"tt-1439"},{"clip":"MF019_1971_CT_SU2011_VA_04","tag":"Imperf","type":"Gram","end":"tt-1441","start":"tt-1441"},{"clip":"MF019_1971_CT_SU2011_VA_04","tag":"MSub","type":"Gram","end":"tt-1444","start":"tt-1444"},{"clip":"MF019_1971_CT_SU2011_VA_04","tag":"MSub:Pret","type":"Gram","end":"tt-1444","start":"tt-1444"},{"clip":"MF019_1971_CT_SU2011_VA_04","tag":"Prep","type":"Gram","end":"tt-1445","start":"tt-1445"},{"clip":"MF019_1971_CT_SU2011_VA_04","tag":"Det","type":"Gram","end":"tt-1446","start":"tt-1446"},{"clip":"MF019_1971_CT_SU2011_VA_04","tag":"Det:Pos","type":"Gram","end":"tt-1446","start":"tt-1446"},{"clip":"MF019_1971_CT_SU2011_VA_04","tag":"Prep","type":"Gram","end":"tt-1451","start":"tt-1451"},{"clip":"MF019_1971_CT_SU2011_VA_04","tag":"Pron","type":"Gram","end":"tt-1452","start":"tt-1452"},{"clip":"MF019_1971_CT_SU2011_VA_04","tag":"Pron:Sujeto","type":"Gram","end":"tt-1452","start":"tt-1452"},{"clip":"MF019_1971_CT_SU2011_VA_04","tag":"Det","type":"Gram","end":"tt-1456","start":"tt-1456"},{"clip":"MF019_1971_CT_SU2011_VA_04","tag":"Det:Pos","type":"Gram","end":"tt-1456","start":"tt-1456"},{"clip":"MF019_1971_CT_SU2011_VA_04","tag":"SerEstar","type":"Gram","end":"tt-1461","start":"tt-1461"},{"clip":"MF019_1971_CT_SU2011_VA_04","tag":"SerEstar:Ser","type":"Gram","end":"tt-1461","start":"tt-1461"},{"clip":"MF019_1971_CT_SU2011_VA_04","tag":"MarcadoresDisc","type":"Prag","end":"tt-1464","start":"tt-1464"},{"clip":"MF019_1971_CT_SU2011_VA_04","tag":"MarcadoresDisc:Igualdad","type":"Prag","end":"tt-1464","start":"tt-1464"},{"clip":"MF019_1971_CT_SU2011_VA_04","tag":"Prep","type":"Gram","end":"tt-1467","start":"tt-1467"},{"clip":"MF019_1971_CT_SU2011_VA_04","tag":"SerEstar","type":"Gram","end":"tt-1472","start":"tt-1472"},{"clip":"MF019_1971_CT_SU2011_VA_04","tag":"SerEstar:Ser","type":"Gram","end":"tt-1472","start":"tt-1472"},{"clip":"MF019_1971_CT_SU2011_VA_04","tag":"Prep","type":"Gram","end":"tt-1479","start":"tt-1479"},{"clip":"MF019_1971_CT_SU2011_VA_04","tag":"Prep:Para","type":"Gram","end":"tt-1479","start":"tt-1479"},{"clip":"MF019_1971_CT_SU2011_VA_04","tag":"MSub","type":"Gram","end":"tt-1481","start":"tt-1481"},{"clip":"MF019_1971_CT_SU2011_VA_04","tag":"MSub:Pret","type":"Gram","end":"tt-1481","start":"tt-1481"},{"clip":"MF019_1971_CT_SU2011_VA_04","tag":"Det","type":"Gram","end":"tt-1482","start":"tt-1482"},{"clip":"MF019_1971_CT_SU2011_VA_04","tag":"Det:Pron","type":"Gram","end":"tt-1482","start":"tt-1482"},{"clip":"MF019_1971_CT_SU2011_VA_04","tag":"Prep","type":"Gram","end":"tt-1483","start":"tt-1483"},{"clip":"MF019_1971_CT_SU2011_VA_04","tag":"Imperf","type":"Gram","end":"tt-1485","start":"tt-1485"},{"clip":"MF019_1971_CT_SU2011_VA_04","tag":"SerEstar","type":"Gram","end":"tt-1485","start":"tt-1485"},{"clip":"MF019_1971_CT_SU2011_VA_04","tag":"SerEstar:Ser","type":"Gram","end":"tt-1485","start":"tt-1485"},{"clip":"MF019_1971_CT_SU2011_VA_04","tag":"Prep","type":"Gram","end":"tt-1489","start":"tt-1489"},{"clip":"MF019_1971_CT_SU2011_VA_04","tag":"Prep","type":"Gram","end":"tt-1490","start":"tt-1490"},{"clip":"MF019_1971_CT_SU2011_VA_04","tag":"Imperf","type":"Gram","end":"tt-1493","start":"tt-1493"},{"clip":"MF019_1971_CT_SU2011_VA_04","tag":"Prep","type":"Gram","end":"tt-1494","start":"tt-1494"},{"clip":"MF019_1971_CT_SU2011_VA_04","tag":"Det","type":"Gram","end":"tt-1496","start":"tt-1496"},{"clip":"MF019_1971_CT_SU2011_VA_04","tag":"Det:Pron","type":"Gram","end":"tt-1496","start":"tt-1496"},{"clip":"MF019_1971_CT_SU2011_VA_04","tag":"Prep","type":"Gram","end":"tt-1497","start":"tt-1497"},{"clip":"MF019_1971_CT_SU2011_VA_04","tag":"MSub","type":"Gram","end":"tt-1499","start":"tt-1499"},{"clip":"MF019_1971_CT_SU2011_VA_04","tag":"MSub:Pres","type":"Gram","end":"tt-1499","start":"tt-1499"},{"clip":"MF019_1971_CT_SU2011_VA_04","tag":"MarcadoresDisc","type":"Prag","end":"tt-1501","start":"tt-1501"},{"clip":"MF019_1971_CT_SU2011_VA_04","tag":"MarcadoresDisc:Revision","type":"Prag","end":"tt-1501","start":"tt-1501"},{"clip":"MF019_1971_CT_SU2011_VA_04","tag":"SerEstar","type":"Gram","end":"tt-1504","start":"tt-1504"},{"clip":"MF019_1971_CT_SU2011_VA_04","tag":"SerEstar:Ser","type":"Gram","end":"tt-1504","start":"tt-1504"},{"clip":"MF019_1971_CT_SU2011_VA_04","tag":"Prep","type":"Gram","end":"tt-1506","start":"tt-1506"},{"clip":"MF019_1971_CT_SU2011_VA_04","tag":"Pron","type":"Gram","end":"tt-1507","start":"tt-1507"},{"clip":"MF019_1971_CT_SU2011_VA_04","tag":"Pron:Sujeto","type":"Gram","end":"tt-1507","start":"tt-1507"},{"clip":"MF019_1971_CT_SU2011_VA_04","tag":"SerEstar","type":"Gram","end":"tt-1508","start":"tt-1508"},{"clip":"MF019_1971_CT_SU2011_VA_04","tag":"SerEstar:Ser","type":"Gram","end":"tt-1508","start":"tt-1508"},{"clip":"MF019_1971_CT_SU2011_VA_04","tag":"Prep","type":"Gram","end":"tt-1510","start":"tt-1510"},{"clip":"MF019_1971_CT_SU2011_VA_04","tag":"Det","type":"Gram","end":"tt-1511","start":"tt-1511"},{"clip":"MF019_1971_CT_SU2011_VA_04","tag":"Det:CuantIndef","type":"Gram","end":"tt-1511","start":"tt-1511"},{"clip":"MF019_1971_CT_SU2011_VA_04","tag":"Det","type":"Gram","end":"tt-1514","start":"tt-1514"},{"clip":"MF019_1971_CT_SU2011_VA_04","tag":"Det:Art","type":"Gram","end":"tt-1514","start":"tt-1514"},{"clip":"MF019_1971_CT_SU2011_VA_04","tag":"Imperf","type":"Gram","end":"tt-1516","start":"tt-1516"},{"clip":"MF019_1971_CT_SU2011_VA_04","tag":"Prep","type":"Gram","end":"tt-1517","start":"tt-1517"},{"clip":"MF019_1971_CT_SU2011_VA_04","tag":"Imperf","type":"Gram","end":"tt-1519","start":"tt-1519"},{"clip":"MF019_1971_CT_SU2011_VA_04","tag":"SerEstar","type":"Gram","end":"tt-1520","start":"tt-1520"},{"clip":"MF019_1971_CT_SU2011_VA_04","tag":"SerEstar:Estar","type":"Gram","end":"tt-1520","start":"tt-1520"},{"clip":"MF019_1971_CT_SU2011_VA_04","tag":"Prep","type":"Gram","end":"tt-1522","start":"tt-1522"},{"clip":"MF019_1971_CT_SU2011_VA_04","tag":"Pron","type":"Gram","end":"tt-1529","start":"tt-1529"},{"clip":"MF019_1971_CT_SU2011_VA_04","tag":"Pron:Sujeto","type":"Gram","end":"tt-1529","start":"tt-1529"},{"clip":"MF019_1971_CT_SU2011_VA_04","tag":"Imperf","type":"Gram","end":"tt-1530","start":"tt-1530"},{"clip":"MF019_1971_CT_SU2011_VA_04","tag":"Prep","type":"Gram","end":"tt-1534","start":"tt-1534"},{"clip":"MF019_1971_CT_SU2011_VA_04","tag":"Pron","type":"Gram","end":"tt-1543","start":"tt-1543"},{"clip":"MF019_1971_CT_SU2011_VA_04","tag":"Pron:Objeto","type":"Gram","end":"tt-1543","start":"tt-1543"},{"clip":"MF019_1971_CT_SU2011_VA_04","tag":"Det","type":"Gram","end":"tt-1545","start":"tt-1545"},{"clip":"MF019_1971_CT_SU2011_VA_04","tag":"Det:Art","type":"Gram","end":"tt-1545","start":"tt-1545"},{"clip":"MF019_1971_CT_SU2011_VA_04","tag":"MarcadoresDisc","type":"Prag","end":"tt-1547","start":"tt-1547"},{"clip":"MF019_1971_CT_SU2011_VA_04","tag":"MarcadoresDisc:Causa","type":"Prag","end":"tt-1547","start":"tt-1547"},{"clip":"MF019_1971_CT_SU2011_VA_04","tag":"Det","type":"Gram","end":"tt-1550","start":"tt-1550"},{"clip":"MF019_1971_CT_SU2011_VA_04","tag":"Det:Art","type":"Gram","end":"tt-1550","start":"tt-1550"},{"clip":"MF019_1971_CT_SU2011_VA_04","tag":"Det","type":"Gram","end":"tt-1552","start":"tt-1552"},{"clip":"MF019_1971_CT_SU2011_VA_04","tag":"Det:Art","type":"Gram","end":"tt-1552","start":"tt-1552"},{"clip":"MF019_1971_CT_SU2011_VA_04","tag":"Imperf","type":"Gram","end":"tt-1558","start":"tt-1558"},{"clip":"MF019_1971_CT_SU2011_VA_04","tag":"Det","type":"Gram","end":"tt-1559","start":"tt-1559"},{"clip":"MF019_1971_CT_SU2011_VA_04","tag":"Det:Pron","type":"Gram","end":"tt-1559","start":"tt-1559"},{"clip":"MF019_1971_CT_SU2011_VA_04","tag":"Prep","type":"Gram","end":"tt-1560","start":"tt-1560"},{"clip":"MF019_1971_CT_SU2011_VA_04","tag":"Prep:Para","type":"Gram","end":"tt-1560","start":"tt-1560"},{"clip":"MF019_1971_CT_SU2011_VA_04","tag":"MSub","type":"Gram","end":"tt-1561","start":"tt-1561"},{"clip":"MF019_1971_CT_SU2011_VA_04","tag":"MSub:Pres","type":"Gram","end":"tt-1561","start":"tt-1561"},{"clip":"MF019_1971_CT_SU2011_VA_04","tag":"Prep","type":"Gram","end":"tt-1565","start":"tt-1565"},{"clip":"MF019_1971_CT_SU2011_VA_04","tag":"SerEstar","type":"Gram","end":"tt-1571","start":"tt-1571"},{"clip":"MF019_1971_CT_SU2011_VA_04","tag":"SerEstar:Ser","type":"Gram","end":"tt-1571","start":"tt-1571"},{"clip":"MF019_1971_CT_SU2011_VA_04","tag":"Pron","type":"Gram","end":"tt-1580","start":"tt-1580"},{"clip":"MF019_1971_CT_SU2011_VA_04","tag":"Pron:Sujeto","type":"Gram","end":"tt-1580","start":"tt-1580"},{"clip":"MF019_1971_CT_SU2011_VA_04","tag":"Imperf","type":"Gram","end":"tt-1581","start":"tt-1581"},{"clip":"MF019_1971_CT_SU2011_VA_04","tag":"SerEstar","type":"Gram","end":"tt-1581","start":"tt-1581"},{"clip":"MF019_1971_CT_SU2011_VA_04","tag":"SerEstar:Ser","type":"Gram","end":"tt-1581","start":"tt-1581"},{"clip":"MF019_1971_CT_SU2011_VA_04","tag":"Det","type":"Gram","end":"tt-1582","start":"tt-1582"},{"clip":"MF019_1971_CT_SU2011_VA_04","tag":"Det:Art","type":"Gram","end":"tt-1582","start":"tt-1582"},{"clip":"MF019_1971_CT_SU2011_VA_04","tag":"Imperf","type":"Gram","end":"tt-1584","start":"tt-1584"},{"clip":"MF019_1971_CT_SU2011_VA_04","tag":"SerEstar","type":"Gram","end":"tt-1584","start":"tt-1584"},{"clip":"MF019_1971_CT_SU2011_VA_04","tag":"SerEstar:Ser","type":"Gram","end":"tt-1584","start":"tt-1584"},{"clip":"MF019_1971_CT_SU2011_VA_04","tag":"Imperf","type":"Gram","end":"tt-1588","start":"tt-1588"},{"clip":"MF019_1971_CT_SU2011_VA_04","tag":"SerEstar","type":"Gram","end":"tt-1588","start":"tt-1588"},{"clip":"MF019_1971_CT_SU2011_VA_04","tag":"SerEstar:Ser","type":"Gram","end":"tt-1588","start":"tt-1588"},{"clip":"MF019_1971_CT_SU2011_VA_04","tag":"Det","type":"Gram","end":"tt-1589","start":"tt-1589"},{"clip":"MF019_1971_CT_SU2011_VA_04","tag":"Det:Art","type":"Gram","end":"tt-1589","start":"tt-1589"},{"clip":"MF019_1971_CT_SU2011_VA_04","tag":"Pron","type":"Gram","end":"tt-1591","start":"tt-1591"},{"clip":"MF019_1971_CT_SU2011_VA_04","tag":"Pron:Sujeto","type":"Gram","end":"tt-1591","start":"tt-1591"},{"clip":"MF019_1971_CT_SU2011_VA_04","tag":"Imperf","type":"Gram","end":"tt-1592","start":"tt-1592"},{"clip":"MF019_1971_CT_SU2011_VA_04","tag":"Det","type":"Gram","end":"tt-1593","start":"tt-1593"},{"clip":"MF019_1971_CT_SU2011_VA_04","tag":"Det:Art","type":"Gram","end":"tt-1593","start":"tt-1593"},{"clip":"MF019_1971_CT_SU2011_VA_04","tag":"MarcadoresDisc","type":"Prag","end":"tt-1595","start":"tt-1595"},{"clip":"MF019_1971_CT_SU2011_VA_04","tag":"MarcadoresDisc:Causa","type":"Prag","end":"tt-1595","start":"tt-1595"},{"clip":"MF019_1971_CT_SU2011_VA_04","tag":"Imperf","type":"Gram","end":"tt-1596","start":"tt-1596"},{"clip":"MF019_1971_CT_SU2011_VA_04","tag":"SerEstar","type":"Gram","end":"tt-1596","start":"tt-1596"},{"clip":"MF019_1971_CT_SU2011_VA_04","tag":"SerEstar:Ser","type":"Gram","end":"tt-1596","start":"tt-1596"},{"clip":"MF019_1971_CT_SU2011_VA_04","tag":"Det","type":"Gram","end":"tt-1597","start":"tt-1597"},{"clip":"MF019_1971_CT_SU2011_VA_04","tag":"Det:Art","type":"Gram","end":"tt-1597","start":"tt-1597"},{"clip":"MF019_1971_CT_SU2011_VA_04","tag":"Det","type":"Gram","end":"tt-1600","start":"tt-1600"},{"clip":"MF019_1971_CT_SU2011_VA_04","tag":"Det:Art","type":"Gram","end":"tt-1600","start":"tt-1600"},{"clip":"MF019_1971_CT_SU2011_VA_04","tag":"Imperf","type":"Gram","end":"tt-1606","start":"tt-1606"},{"clip":"MF019_1971_CT_SU2011_VA_04","tag":"Prep","type":"Gram","end":"tt-1610","start":"tt-1610"},{"clip":"MF019_1971_CT_SU2011_VA_04","tag":"Prep","type":"Gram","end":"tt-1612","start":"tt-1612"},{"clip":"MF019_1971_CT_SU2011_VA_04","tag":"Imperf","type":"Gram","end":"tt-1614","start":"tt-1614"},{"clip":"MF019_1971_CT_SU2011_VA_04","tag":"SerEstar","type":"Gram","end":"tt-1614","start":"tt-1614"},{"clip":"MF019_1971_CT_SU2011_VA_04","tag":"SerEstar:Ser","type":"Gram","end":"tt-1614","start":"tt-1614"},{"clip":"MF019_1971_CT_SU2011_VA_04","tag":"Det","type":"Gram","end":"tt-1615","start":"tt-1615"},{"clip":"MF019_1971_CT_SU2011_VA_04","tag":"Det:Art","type":"Gram","end":"tt-1615","start":"tt-1615"},{"clip":"MF019_1971_CT_SU2011_VA_04","tag":"Det","type":"Gram","end":"tt-1617","start":"tt-1617"},{"clip":"MF019_1971_CT_SU2011_VA_04","tag":"Det:Art","type":"Gram","end":"tt-1617","start":"tt-1617"},{"clip":"MF019_1971_CT_SU2011_VA_04","tag":"Imperf","type":"Gram","end":"tt-1619","start":"tt-1619"},{"clip":"MF019_1971_CT_SU2011_VA_04","tag":"Det","type":"Gram","end":"tt-1621","start":"tt-1621"},{"clip":"MF019_1971_CT_SU2011_VA_04","tag":"Det:Art","type":"Gram","end":"tt-1621","start":"tt-1621"},{"clip":"MF019_1971_CT_SU2011_VA_04","tag":"Det","type":"Gram","end":"tt-1624","start":"tt-1624"},{"clip":"MF019_1971_CT_SU2011_VA_04","tag":"Det:Art","type":"Gram","end":"tt-1624","start":"tt-1624"},{"clip":"MF019_1971_CT_SU2011_VA_04","tag":"Imperf","type":"Gram","end":"tt-1626","start":"tt-1626"},{"clip":"MF019_1971_CT_SU2011_VA_04","tag":"Prep","type":"Gram","end":"tt-1627","start":"tt-1627"},{"clip":"MF019_1971_CT_SU2011_VA_04","tag":"Det","type":"Gram","end":"tt-1635","start":"tt-1635"},{"clip":"MF019_1971_CT_SU2011_VA_04","tag":"Det:Art","type":"Gram","end":"tt-1635","start":"tt-1635"},{"clip":"MF019_1971_CT_SU2011_VA_04","tag":"Pron","type":"Gram","end":"tt-1638","start":"tt-1638"},{"clip":"MF019_1971_CT_SU2011_VA_04","tag":"Pron:Objeto","type":"Gram","end":"tt-1638","start":"tt-1638"},{"clip":"MF019_1971_CT_SU2011_VA_04","tag":"Pron","type":"Gram","end":"tt-1640","start":"tt-1640"},{"clip":"MF019_1971_CT_SU2011_VA_04","tag":"Pron:Objeto","type":"Gram","end":"tt-1640","start":"tt-1640"},{"clip":"MF019_1971_CT_SU2011_VA_04","tag":"Imperf","type":"Gram","end":"tt-1641","start":"tt-1641"},{"clip":"MF019_1971_CT_SU2011_VA_04","tag":"Prep","type":"Gram","end":"tt-1642","start":"tt-1642"},{"clip":"MF019_1971_CT_SU2011_VA_04","tag":"MarcadoresDisc","type":"Prag","end":"tt-1644","start":"tt-1644"},{"clip":"MF019_1971_CT_SU2011_VA_04","tag":"MarcadoresDisc:Causa","type":"Prag","end":"tt-1644","start":"tt-1644"},{"clip":"MF019_1971_CT_SU2011_VA_04","tag":"Imperf","type":"Gram","end":"tt-1646","start":"tt-1646"},{"clip":"MF019_1971_CT_SU2011_VA_04","tag":"SerEstar","type":"Gram","end":"tt-1646","start":"tt-1646"},{"clip":"MF019_1971_CT_SU2011_VA_04","tag":"SerEstar:Ser","type":"Gram","end":"tt-1646","start":"tt-1646"},{"clip":"MF019_1971_CT_SU2011_VA_04","tag":"Det","type":"Gram","end":"tt-1647","start":"tt-1647"},{"clip":"MF019_1971_CT_SU2011_VA_04","tag":"Det:Art","type":"Gram","end":"tt-1647","start":"tt-1647"},{"clip":"MF019_1971_CT_SU2011_VA_04","tag":"Pron","type":"Gram","end":"tt-1655","start":"tt-1655"},{"clip":"MF019_1971_CT_SU2011_VA_04","tag":"Pron:Objeto","type":"Gram","end":"tt-1655","start":"tt-1655"},{"clip":"MF019_1971_CT_SU2011_VA_04","tag":"Imperf","type":"Gram","end":"tt-1656","start":"tt-1656"},{"clip":"MF019_1971_CT_SU2011_VA_04","tag":"MImp","type":"Gram","end":"tt-1660","start":"tt-1660"},{"clip":"MF019_1971_CT_SU2011_VA_04","tag":"MImp:Informal","type":"Gram","end":"tt-1660","start":"tt-1660"},{"clip":"MF019_1971_CT_SU2011_VA_04","tag":"Prep","type":"Gram","end":"tt-1662","start":"tt-1662"},{"clip":"MF019_1971_CT_SU2011_VA_04","tag":"Imperf","type":"Gram","end":"tt-1669","start":"tt-1669"},{"clip":"MF019_1971_CT_SU2011_VA_04","tag":"SerEstar","type":"Gram","end":"tt-1669","start":"tt-1669"},{"clip":"MF019_1971_CT_SU2011_VA_04","tag":"SerEstar:Ser","type":"Gram","end":"tt-1669","start":"tt-1669"},{"clip":"MF019_1971_CT_SU2011_VA_04","tag":"MarcadoresDisc","type":"Prag","end":"tt-1672","start":"tt-1672"},{"clip":"MF019_1971_CT_SU2011_VA_04","tag":"MarcadoresDisc:Igualdad","type":"Prag","end":"tt-1672","start":"tt-1672"},{"clip":"MF019_1971_CT_SU2011_VA_04","tag":"MarcadoresDisc","type":"Prag","end":"tt-1674","start":"tt-1674"},{"clip":"MF019_1971_CT_SU2011_VA_04","tag":"MarcadoresDisc:Revision","type":"Prag","end":"tt-1674","start":"tt-1674"},{"clip":"MF019_1971_CT_SU2011_VA_04","tag":"Det","type":"Gram","end":"tt-1685","start":"tt-1685"},{"clip":"MF019_1971_CT_SU2011_VA_04","tag":"Det:Art","type":"Gram","end":"tt-1685","start":"tt-1685"},{"clip":"MF019_1971_CT_SU2011_VA_04","tag":"MarcadoresDisc","type":"Prag","end":"tt-1689","start":"tt-1689"},{"clip":"MF019_1971_CT_SU2011_VA_04","tag":"MarcadoresDisc:Revision","type":"Prag","end":"tt-1689","start":"tt-1689"},{"clip":"MF019_1971_CT_SU2011_VA_04","tag":"SerEstar","type":"Gram","end":"tt-1691","start":"tt-1691"},{"clip":"MF019_1971_CT_SU2011_VA_04","tag":"SerEstar:Ser","type":"Gram","end":"tt-1691","start":"tt-1691"},{"clip":"MF019_1971_CT_SU2011_VA_04","tag":"Det","type":"Gram","end":"tt-1699","start":"tt-1699"},{"clip":"MF019_1971_CT_SU2011_VA_04","tag":"Det:Art","type":"Gram","end":"tt-1699","start":"tt-1699"},{"clip":"MF019_1971_CT_SU2011_VA_04","tag":"Det","type":"Gram","end":"tt-1157","start":"tt-1156"},{"clip":"MF019_1971_CT_SU2011_VA_04","tag":"Det:Combi","type":"Gram","end":"tt-1157","start":"tt-1156"},{"clip":"MF019_1971_CT_SU2011_VA_04","tag":"Det","type":"Gram","end":"tt-1250","start":"tt-1249"},{"clip":"MF019_1971_CT_SU2011_VA_04","tag":"Det:Combi","type":"Gram","end":"tt-1250","start":"tt-1249"},{"clip":"MF019_1971_CT_SU2011_VA_04","tag":"Genero","type":"Gram","end":"tt-1417","start":"tt-1416"},{"clip":"MF019_1971_CT_SU2011_VA_04","tag":"Genero:ExcepMasc","type":"Gram","end":"tt-1417","start":"tt-1416"},{"clip":"MF019_1971_CT_SU2011_VA_04","tag":"Det","type":"Gram","end":"tt-1420","start":"tt-1419"},{"clip":"MF019_1971_CT_SU2011_VA_04","tag":"Det:Combi","type":"Gram","end":"tt-1420","start":"tt-1419"},{"clip":"MF019_1971_CT_SU2011_VA_04","tag":"Genero","type":"Gram","end":"tt-1487","start":"tt-1486"},{"clip":"MF019_1971_CT_SU2011_VA_04","tag":"Genero:ExcepMasc","type":"Gram","end":"tt-1487","start":"tt-1486"},{"clip":"MF019_1971_CT_SU2011_VA_04","tag":"Contacto","type":"Herit","end":"tt-1492","start":"tt-1491"},{"clip":"MF019_1971_CT_SU2011_VA_04","tag":"Contacto:Mixtas","type":"Herit","end":"tt-1492","start":"tt-1491"},{"clip":"MF019_1971_CT_SU2011_VA_04","tag":"VFut","type":"Gram","end":"tt-1495","start":"tt-1493"},{"clip":"MF019_1971_CT_SU2011_VA_04","tag":"VFut:Perifrasis","type":"Gram","end":"tt-1495","start":"tt-1493"},{"clip":"MF019_1971_CT_SU2011_VA_04","tag":"Det","type":"Gram","end":"tt-1503","start":"tt-1502"},{"clip":"MF019_1971_CT_SU2011_VA_04","tag":"Det:LoAdj","type":"Gram","end":"tt-1503","start":"tt-1502"},{"clip":"MF019_1971_CT_SU2011_VA_04","tag":"VFut","type":"Gram","end":"tt-1535","start":"tt-1533"},{"clip":"MF019_1971_CT_SU2011_VA_04","tag":"VFut:Perifrasis","type":"Gram","end":"tt-1535","start":"tt-1533"},{"clip":"MF019_1971_CT_SU2011_VA_04","tag":"Det","type":"Gram","end":"tt-1693","start":"tt-1692"},{"clip":"MF019_1971_CT_SU2011_VA_04","tag":"Det:LoAdj","type":"Gram","end":"tt-1693","start":"tt-1692"},{"clip":"MF019_1971_CT_SU2011_VA_04","tag":"Det","type":"Gram","end":"tt-1699","start":"tt-1698"},{"clip":"MF019_1971_CT_SU2011_VA_04","tag":"Det:Combi","type":"Gram","end":"tt-1699","start":"tt-1698"},{"clip":"MF019_1971_CT_SU2011_VA_04","tag":"Adjective:propio","type":"Vocab","end":"tt-1376","start":"tt-1376"},{"clip":"MF019_1971_CT_SU2011_VA_04","tag":"Adjective:serio","type":"Vocab","end":"tt-1221","start":"tt-1221"},{"clip":"MF019_1971_CT_SU2011_VA_04","tag":"Noun:problema","type":"Vocab","end":"tt-1487","start":"tt-1487"},{"clip":"MF019_1971_CT_SU2011_VA_04","tag":"Noun:crisis","type":"Vocab","end":"tt-1512","start":"tt-1512"},{"clip":"MF019_1971_CT_SU2011_VA_04","tag":"Verb:ser","type":"Vocab","end":"tt-1472","start":"tt-1472"},{"clip":"MF019_1971_CT_SU2011_VA_04","tag":"Adjective:verdadero","type":"Vocab","end":"tt-1209","start":"tt-1209"},{"clip":"MF019_1971_CT_SU2011_VA_04","tag":"Verb:quitar","type":"Vocab","end":"tt-1544","start":"tt-1544"},{"clip":"MF019_1971_CT_SU2011_VA_04","tag":"Adjective:grande","type":"Vocab","end":"tt-1687","start":"tt-1687"},{"clip":"MF019_1971_CT_SU2011_VA_04","tag":"Verb:dormir","type":"Vocab","end":"tt-1424","start":"tt-1424"},{"clip":"MF019_1971_CT_SU2011_VA_04","tag":"Verb:UNK","type":"Vocab","end":"tt-1444","start":"tt-1444"},{"clip":"MF019_1971_CT_SU2011_VA_04","tag":"Adjective:serio","type":"Vocab","end":"tt-1176","start":"tt-1176"},{"clip":"MF019_1971_CT_SU2011_VA_04","tag":"Noun:bebé","type":"Vocab","end":"tt-1130","start":"tt-1130"},{"clip":"MF019_1971_CT_SU2011_VA_04","tag":"Noun:Texas","type":"Vocab","end":"tt-1470","start":"tt-1470"},{"clip":"MF019_1971_CT_SU2011_VA_04","tag":"Verb:tensar","type":"Vocab","end":"tt-1298","start":"tt-1298"},{"clip":"MF019_1971_CT_SU2011_VA_04","tag":"Noun:techo","type":"Vocab","end":"tt-1546","start":"tt-1546"},{"clip":"MF019_1971_CT_SU2011_VA_04","tag":"Adjective:último","type":"Vocab","end":"tt-1147","start":"tt-1147"},{"clip":"MF019_1971_CT_SU2011_VA_04","tag":"Noun:UNK","type":"Vocab","end":"tt-1184","start":"tt-1184"},{"clip":"MF019_1971_CT_SU2011_VA_04","tag":"Noun:UNK","type":"Vocab","end":"tt-1566","start":"tt-1566"},{"clip":"MF019_1971_CT_SU2011_VA_04","tag":"Verb:encontrar","type":"Vocab","end":"tt-1495","start":"tt-1495"},{"clip":"MF019_1971_CT_SU2011_VA_04","tag":"Verb:UNK","type":"Vocab","end":"tt-1443","start":"tt-1443"},{"clip":"MF019_1971_CT_SU2011_VA_04","tag":"Verb:quitar","type":"Vocab","end":"tt-1549","start":"tt-1549"},{"clip":"MF019_1971_CT_SU2011_VA_04","tag":"Verb:seguir","type":"Vocab","end":"tt-1567","start":"tt-1567"},{"clip":"MF019_1971_CT_SU2011_VA_04","tag":"Noun:broma","type":"Vocab","end":"tt-1331","start":"tt-1331"},{"clip":"MF019_1971_CT_SU2011_VA_04","tag":"Verb:reír","type":"Vocab","end":"tt-1561","start":"tt-1561"},{"clip":"MF019_1971_CT_SU2011_VA_04","tag":"Noun:UNK","type":"Vocab","end":"tt-1198","start":"tt-1198"},{"clip":"MF019_1971_CT_SU2011_VA_04","tag":"Noun:mundo","type":"Vocab","end":"tt-1377","start":"tt-1377"},{"clip":"MF019_1971_CT_SU2011_VA_04","tag":"Verb:haber","type":"Vocab","end":"tt-1434","start":"tt-1434"},{"clip":"MF019_1971_CT_SU2011_VA_04","tag":"Noun:UNK","type":"Vocab","end":"tt-1576","start":"tt-1576"},{"clip":"MF019_1971_CT_SU2011_VA_04","tag":"Noun:día","type":"Vocab","end":"tt-1417","start":"tt-1417"},{"clip":"MF019_1971_CT_SU2011_VA_04","tag":"Noun:parte","type":"Vocab","end":"tt-1396","start":"tt-1396"},{"clip":"MF019_1971_CT_SU2011_VA_04","tag":"Verb:haber","type":"Vocab","end":"tt-1295","start":"tt-1295"},{"clip":"MF019_1971_CT_SU2011_VA_04","tag":"Verb:hacer","type":"Vocab","end":"tt-1248","start":"tt-1248"},{"clip":"MF019_1971_CT_SU2011_VA_04","tag":"Verb:ser","type":"Vocab","end":"tt-1504","start":"tt-1504"},{"clip":"MF019_1971_CT_SU2011_VA_04","tag":"Noun:veracidad","type":"Vocab","end":"tt-1196","start":"tt-1196"},{"clip":"MF019_1971_CT_SU2011_VA_04","tag":"Adjective:poco","type":"Vocab","end":"tt-1250","start":"tt-1250"},{"clip":"MF019_1971_CT_SU2011_VA_04","tag":"Adjective:funeral","type":"Vocab","end":"tt-1492","start":"tt-1492"},{"clip":"MF019_1971_CT_SU2011_VA_04","tag":"Noun:nombre","type":"Vocab","end":"tt-1188","start":"tt-1188"},{"clip":"MF019_1971_CT_SU2011_VA_04","tag":"Verb:hacer","type":"Vocab","end":"tt-1694","start":"tt-1694"},{"clip":"MF019_1971_CT_SU2011_VA_04","tag":"Verb:cercar","type":"Vocab","end":"tt-1151","start":"tt-1151"},{"clip":"MF019_1971_CT_SU2011_VA_04","tag":"Verb:tener","type":"Vocab","end":"tt-1069","start":"tt-1069"},{"clip":"MF019_1971_CT_SU2011_VA_04","tag":"Verb:ser","type":"Vocab","end":"tt-1286","start":"tt-1286"},{"clip":"MF019_1971_CT_SU2011_VA_04","tag":"Noun:momento","type":"Vocab","end":"tt-1297","start":"tt-1297"},{"clip":"MF019_1971_CT_SU2011_VA_04","tag":"Noun:felicidad","type":"Vocab","end":"tt-1210","start":"tt-1210"},{"clip":"MF019_1971_CT_SU2011_VA_04","tag":"Verb:ir","type":"Vocab","end":"tt-1619","start":"tt-1619"},{"clip":"MF019_1971_CT_SU2011_VA_04","tag":"Adjective:grande","type":"Vocab","end":"tt-1095","start":"tt-1095"},{"clip":"MF019_1971_CT_SU2011_VA_04","tag":"Verb:saber","type":"Vocab","end":"tt-1450","start":"tt-1450"},{"clip":"MF019_1971_CT_SU2011_VA_04","tag":"Verb:ser","type":"Vocab","end":"tt-1323","start":"tt-1323"},{"clip":"MF019_1971_CT_SU2011_VA_04","tag":"Verb:ser","type":"Vocab","end":"tt-1218","start":"tt-1218"},{"clip":"MF019_1971_CT_SU2011_VA_04","tag":"Noun:broma","type":"Vocab","end":"tt-1305","start":"tt-1305"},{"clip":"MF019_1971_CT_SU2011_VA_04","tag":"Verb:poder","type":"Vocab","end":"tt-1339","start":"tt-1339"},{"clip":"MF019_1971_CT_SU2011_VA_04","tag":"Verb:tener","type":"Vocab","end":"tt-1102","start":"tt-1102"},{"clip":"MF019_1971_CT_SU2011_VA_04","tag":"Adjective:último","type":"Vocab","end":"tt-1598","start":"tt-1598"},{"clip":"MF019_1971_CT_SU2011_VA_04","tag":"Verb:decir","type":"Vocab","end":"tt-1592","start":"tt-1592"},{"clip":"MF019_1971_CT_SU2011_VA_04","tag":"Verb:ir","type":"Vocab","end":"tt-1533","start":"tt-1533"},{"clip":"MF019_1971_CT_SU2011_VA_04","tag":"Noun:ay","type":"Vocab","end":"tt-1238","start":"tt-1238"},{"clip":"MF019_1971_CT_SU2011_VA_04","tag":"Verb:caminar","type":"Vocab","end":"tt-1661","start":"tt-1661"},{"clip":"MF019_1971_CT_SU2011_VA_04","tag":"Adjective:único","type":"Vocab","end":"tt-1381","start":"tt-1381"},{"clip":"MF019_1971_CT_SU2011_VA_04","tag":"Verb:seguir","type":"Vocab","end":"tt-1273","start":"tt-1273"},{"clip":"MF019_1971_CT_SU2011_VA_04","tag":"Noun:frente","type":"Vocab","end":"tt-1663","start":"tt-1663"},{"clip":"MF019_1971_CT_SU2011_VA_04","tag":"Verb:tensar","type":"Vocab","end":"tt-1525","start":"tt-1525"},{"clip":"MF019_1971_CT_SU2011_VA_04","tag":"Noun:Lucy","type":"Vocab","end":"tt-1277","start":"tt-1277"},{"clip":"MF019_1971_CT_SU2011_VA_04","tag":"Adjective:junto","type":"Vocab","end":"tt-1399","start":"tt-1399"},{"clip":"MF019_1971_CT_SU2011_VA_04","tag":"Noun:Alina","type":"Vocab","end":"tt-1666","start":"tt-1666"},{"clip":"MF019_1971_CT_SU2011_VA_04","tag":"Noun:veracidad","type":"Vocab","end":"tt-1194","start":"tt-1194"},{"clip":"MF019_1971_CT_SU2011_VA_04","tag":"Noun:UNK","type":"Vocab","end":"tt-1570","start":"tt-1570"},{"clip":"MF019_1971_CT_SU2011_VA_04","tag":"Noun:muchacho","type":"Vocab","end":"tt-1636","start":"tt-1636"},{"clip":"MF019_1971_CT_SU2011_VA_04","tag":"Noun:personalidad","type":"Vocab","end":"tt-1608","start":"tt-1608"},{"clip":"MF019_1971_CT_SU2011_VA_04","tag":"Noun:UNK","type":"Vocab","end":"tt-1190","start":"tt-1190"},{"clip":"MF019_1971_CT_SU2011_VA_04","tag":"Verb:nacer","type":"Vocab","end":"tt-1133","start":"tt-1133"},{"clip":"MF019_1971_CT_SU2011_VA_04","tag":"Verb:ser","type":"Vocab","end":"tt-1254","start":"tt-1254"},{"clip":"MF019_1971_CT_SU2011_VA_04","tag":"Noun:felicidad","type":"Vocab","end":"tt-1257","start":"tt-1257"},{"clip":"MF019_1971_CT_SU2011_VA_04","tag":"Adjective:verdadero","type":"Vocab","end":"tt-1256","start":"tt-1256"},{"clip":"MF019_1971_CT_SU2011_VA_04","tag":"Noun:UNK","type":"Vocab","end":"tt-1651","start":"tt-1651"},{"clip":"MF019_1971_CT_SU2011_VA_04","tag":"Verb:ser","type":"Vocab","end":"tt-1085","start":"tt-1085"},{"clip":"MF019_1971_CT_SU2011_VA_04","tag":"Verb:entrar","type":"Vocab","end":"tt-1388","start":"tt-1388"},{"clip":"MF019_1971_CT_SU2011_VA_04","tag":"Noun:UNK","type":"Vocab","end":"tt-1632","start":"tt-1632"},{"clip":"MF019_1971_CT_SU2011_VA_04","tag":"Noun:inglés","type":"Vocab","end":"tt-1200","start":"tt-1200"},{"clip":"MF019_1971_CT_SU2011_VA_04","tag":"Verb:dormir","type":"Vocab","end":"tt-1401","start":"tt-1401"},{"clip":"MF019_1971_CT_SU2011_VA_04","tag":"Verb:ser","type":"Vocab","end":"tt-1669","start":"tt-1669"},{"clip":"MF019_1971_CT_SU2011_VA_04","tag":"Verb:hacer","type":"Vocab","end":"tt-1329","start":"tt-1329"},{"clip":"MF019_1971_CT_SU2011_VA_04","tag":"Verb:tratar","type":"Vocab","end":"tt-1309","start":"tt-1309"},{"clip":"MF019_1971_CT_SU2011_VA_04","tag":"Verb:decir","type":"Vocab","end":"tt-1064","start":"tt-1064"},{"clip":"MF019_1971_CT_SU2011_VA_04","tag":"Verb:significar","type":"Vocab","end":"tt-1193","start":"tt-1193"},{"clip":"MF019_1971_CT_SU2011_VA_04","tag":"Verb:tener","type":"Vocab","end":"tt-1606","start":"tt-1606"},{"clip":"MF019_1971_CT_SU2011_VA_04","tag":"Verb:poner","type":"Vocab","end":"tt-1658","start":"tt-1658"},{"clip":"MF019_1971_CT_SU2011_VA_04","tag":"Verb:significar","type":"Vocab","end":"tt-1189","start":"tt-1189"},{"clip":"MF019_1971_CT_SU2011_VA_04","tag":"Verb:ser","type":"Vocab","end":"tt-1212","start":"tt-1212"},{"clip":"MF019_1971_CT_SU2011_VA_04","tag":"Verb:que","type":"Vocab","end":"tt-1322","start":"tt-1322"},{"clip":"MF019_1971_CT_SU2011_VA_04","tag":"Noun:UNK","type":"Vocab","end":"tt-1252","start":"tt-1252"},{"clip":"MF019_1971_CT_SU2011_VA_04","tag":"Verb:poder","type":"Vocab","end":"tt-1263","start":"tt-1263"},{"clip":"MF019_1971_CT_SU2011_VA_04","tag":"Noun:resto","type":"Vocab","end":"tt-1361","start":"tt-1361"},{"clip":"MF019_1971_CT_SU2011_VA_04","tag":"Verb:poder","type":"Vocab","end":"tt-1519","start":"tt-1519"},{"clip":"MF019_1971_CT_SU2011_VA_04","tag":"Noun:período","type":"Vocab","end":"tt-1142","start":"tt-1142"},{"clip":"MF019_1971_CT_SU2011_VA_04","tag":"Verb:estar","type":"Vocab","end":"tt-1520","start":"tt-1520"},{"clip":"MF019_1971_CT_SU2011_VA_04","tag":"Adjective:bonito","type":"Vocab","end":"tt-1648","start":"tt-1648"},{"clip":"MF019_1971_CT_SU2011_VA_04","tag":"Noun:UNK","type":"Vocab","end":"tt-1315","start":"tt-1315"},{"clip":"MF019_1971_CT_SU2011_VA_04","tag":"Noun:ay","type":"Vocab","end":"tt-1531","start":"tt-1531"},{"clip":"MF019_1971_CT_SU2011_VA_04","tag":"Verb:soltar","type":"Vocab","end":"tt-1335","start":"tt-1335"},{"clip":"MF019_1971_CT_SU2011_VA_04","tag":"Noun:instinto","type":"Vocab","end":"tt-1357","start":"tt-1357"},{"clip":"MF019_1971_CT_SU2011_VA_04","tag":"Noun:broma","type":"Vocab","end":"tt-1235","start":"tt-1235"},{"clip":"MF019_1971_CT_SU2011_VA_04","tag":"Noun:hermano","type":"Vocab","end":"tt-1136","start":"tt-1136"},{"clip":"MF019_1971_CT_SU2011_VA_04","tag":"Noun:niño","type":"Vocab","end":"tt-1594","start":"tt-1594"},{"clip":"MF019_1971_CT_SU2011_VA_04","tag":"Verb:haber","type":"Vocab","end":"tt-1118","start":"tt-1118"},{"clip":"MF019_1971_CT_SU2011_VA_04","tag":"Noun:diferencia","type":"Vocab","end":"tt-1078","start":"tt-1078"},{"clip":"MF019_1971_CT_SU2011_VA_04","tag":"Verb:ser","type":"Vocab","end":"tt-1646","start":"tt-1646"},{"clip":"MF019_1971_CT_SU2011_VA_04","tag":"Adjective:chico","type":"Vocab","end":"tt-1602","start":"tt-1602"},{"clip":"MF019_1971_CT_SU2011_VA_04","tag":"Verb:ser","type":"Vocab","end":"tt-1400","start":"tt-1400"},{"clip":"MF019_1971_CT_SU2011_VA_04","tag":"Noun:hermano","type":"Vocab","end":"tt-1053","start":"tt-1053"},{"clip":"MF019_1971_CT_SU2011_VA_04","tag":"Verb:UNK","type":"Vocab","end":"tt-1631","start":"tt-1631"},{"clip":"MF019_1971_CT_SU2011_VA_04","tag":"Verb:ir","type":"Vocab","end":"tt-1493","start":"tt-1493"},{"clip":"MF019_1971_CT_SU2011_VA_04","tag":"Verb:significar","type":"Vocab","end":"tt-1205","start":"tt-1205"},{"clip":"MF019_1971_CT_SU2011_VA_04","tag":"Noun:chispa","type":"Vocab","end":"tt-1474","start":"tt-1474"},{"clip":"MF019_1971_CT_SU2011_VA_04","tag":"Noun:reja","type":"Vocab","end":"tt-1435","start":"tt-1435"},{"clip":"MF019_1971_CT_SU2011_VA_04","tag":"Verb:reír","type":"Vocab","end":"tt-1290","start":"tt-1290"},{"clip":"MF019_1971_CT_SU2011_VA_04","tag":"Noun:hermano","type":"Vocab","end":"tt-1158","start":"tt-1158"},{"clip":"MF019_1971_CT_SU2011_VA_04","tag":"Verb:crecer","type":"Vocab","end":"tt-1398","start":"tt-1398"},{"clip":"MF019_1971_CT_SU2011_VA_04","tag":"Verb:querer","type":"Vocab","end":"tt-1441","start":"tt-1441"},{"clip":"MF019_1971_CT_SU2011_VA_04","tag":"Noun:arquitecto","type":"Vocab","end":"tt-1572","start":"tt-1572"},{"clip":"MF019_1971_CT_SU2011_VA_04","tag":"Verb:tomar","type":"Vocab","end":"tt-1481","start":"tt-1481"},{"clip":"MF019_1971_CT_SU2011_VA_04","tag":"Verb:ser","type":"Vocab","end":"tt-1183","start":"tt-1183"},{"clip":"MF019_1971_CT_SU2011_VA_04","tag":"Noun:UNK","type":"Vocab","end":"tt-1628","start":"tt-1628"},{"clip":"MF019_1971_CT_SU2011_VA_04","tag":"Adjective:increíble","type":"Vocab","end":"tt-1505","start":"tt-1505"},{"clip":"MF019_1971_CT_SU2011_VA_04","tag":"Adjective:último","type":"Vocab","end":"tt-1058","start":"tt-1058"},{"clip":"MF019_1971_CT_SU2011_VA_04","tag":"Verb:cerrar","type":"Vocab","end":"tt-1431","start":"tt-1431"},{"clip":"MF019_1971_CT_SU2011_VA_04","tag":"Noun:hermano","type":"Vocab","end":"tt-1108","start":"tt-1108"},{"clip":"MF019_1971_CT_SU2011_VA_04","tag":"Verb:ser","type":"Vocab","end":"tt-1584","start":"tt-1584"},{"clip":"MF019_1971_CT_SU2011_VA_04","tag":"Verb:ser","type":"Vocab","end":"tt-1407","start":"tt-1407"},{"clip":"MF019_1971_CT_SU2011_VA_04","tag":"Verb:tener","type":"Vocab","end":"tt-1159","start":"tt-1159"},{"clip":"MF019_1971_CT_SU2011_VA_04","tag":"Noun:muchacho","type":"Vocab","end":"tt-1618","start":"tt-1618"},{"clip":"MF019_1971_CT_SU2011_VA_04","tag":"Verb:UNK","type":"Vocab","end":"tt-1145","start":"tt-1145"},{"clip":"MF019_1971_CT_SU2011_VA_04","tag":"Noun:casa","type":"Vocab","end":"tt-1301","start":"tt-1301"},{"clip":"MF019_1971_CT_SU2011_VA_04","tag":"Verb:poder","type":"Vocab","end":"tt-1083","start":"tt-1083"},{"clip":"MF019_1971_CT_SU2011_VA_04","tag":"Verb:vivir","type":"Vocab","end":"tt-1465","start":"tt-1465"},{"clip":"MF019_1971_CT_SU2011_VA_04","tag":"Verb:nacer","type":"Vocab","end":"tt-1074","start":"tt-1074"},{"clip":"MF019_1971_CT_SU2011_VA_04","tag":"Noun:recámara","type":"Vocab","end":"tt-1447","start":"tt-1447"},{"clip":"MF019_1971_CT_SU2011_VA_04","tag":"Noun:UNK","type":"Vocab","end":"tt-1568","start":"tt-1568"},{"clip":"MF019_1971_CT_SU2011_VA_04","tag":"Adjective:serio","type":"Vocab","end":"tt-1244","start":"tt-1244"},{"clip":"MF019_1971_CT_SU2011_VA_04","tag":"Verb:platicar","type":"Vocab","end":"tt-1410","start":"tt-1410"},{"clip":"MF019_1971_CT_SU2011_VA_04","tag":"Verb:caer","type":"Vocab","end":"tt-1555","start":"tt-1555"},{"clip":"MF019_1971_CT_SU2011_VA_04","tag":"Noun:Leticia","type":"Vocab","end":"tt-1185","start":"tt-1185"},{"clip":"MF019_1971_CT_SU2011_VA_04","tag":"Verb:vivir","type":"Vocab","end":"tt-1373","start":"tt-1373"},{"clip":"MF019_1971_CT_SU2011_VA_04","tag":"Verb:haber","type":"Vocab","end":"tt-1084","start":"tt-1084"},{"clip":"MF019_1971_CT_SU2011_VA_04","tag":"Noun:familia","type":"Vocab","end":"tt-1696","start":"tt-1696"},{"clip":"MF019_1971_CT_SU2011_VA_04","tag":"Noun:reclusorio","type":"Vocab","end":"tt-1428","start":"tt-1428"},{"clip":"MF019_1971_CT_SU2011_VA_04","tag":"Verb:llamar","type":"Vocab","end":"tt-1215","start":"tt-1215"},{"clip":"MF019_1971_CT_SU2011_VA_04","tag":"Noun:tiempo","type":"Vocab","end":"tt-1144","start":"tt-1144"},{"clip":"MF019_1971_CT_SU2011_VA_04","tag":"Noun:Leticia","type":"Vocab","end":"tt-1203","start":"tt-1203"},{"clip":"MF019_1971_CT_SU2011_VA_04","tag":"Verb:poder","type":"Vocab","end":"tt-1341","start":"tt-1341"},{"clip":"MF019_1971_CT_SU2011_VA_04","tag":"Verb:haber","type":"Vocab","end":"tt-1129","start":"tt-1129"},{"clip":"MF019_1971_CT_SU2011_VA_04","tag":"Noun:UNK","type":"Vocab","end":"tt-1645","start":"tt-1645"},{"clip":"MF019_1971_CT_SU2011_VA_04","tag":"Verb:dejar","type":"Vocab","end":"tt-1660","start":"tt-1660"},{"clip":"MF019_1971_CT_SU2011_VA_04","tag":"Verb:nacer","type":"Vocab","end":"tt-1114","start":"tt-1114"},{"clip":"MF019_1971_CT_SU2011_VA_04","tag":"Noun:Lucy","type":"Vocab","end":"tt-1274","start":"tt-1274"},{"clip":"MF019_1971_CT_SU2011_VA_04","tag":"Verb:hacer","type":"Vocab","end":"tt-1535","start":"tt-1535"},{"clip":"MF019_1971_CT_SU2011_VA_04","tag":"Verb:ir","type":"Vocab","end":"tt-1414","start":"tt-1414"},{"clip":"MF019_1971_CT_SU2011_VA_04","tag":"Verb:hacer","type":"Vocab","end":"tt-1289","start":"tt-1289"},{"clip":"MF019_1971_CT_SU2011_VA_04","tag":"Verb:tomar","type":"Vocab","end":"tt-1240","start":"tt-1240"},{"clip":"MF019_1971_CT_SU2011_VA_04","tag":"Verb:reír","type":"Vocab","end":"tt-1336","start":"tt-1336"},{"clip":"MF019_1971_CT_SU2011_VA_04","tag":"Noun:Jorge","type":"Vocab","end":"tt-1371","start":"tt-1371"},{"clip":"MF019_1971_CT_SU2011_VA_04","tag":"Adjective:distinto","type":"Vocab","end":"tt-1700","start":"tt-1700"},{"clip":"MF019_1971_CT_SU2011_VA_04","tag":"Verb:seguir","type":"Vocab","end":"tt-1459","start":"tt-1459"},{"clip":"MF019_1971_CT_SU2011_VA_04","tag":"Adjective:grande","type":"Vocab","end":"tt-1182","start":"tt-1182"},{"clip":"MF019_1971_CT_SU2011_VA_04","tag":"Noun:muchacho","type":"Vocab","end":"tt-1625","start":"tt-1625"},{"clip":"MF019_1971_CT_SU2011_VA_04","tag":"Verb:tener","type":"Vocab","end":"tt-1516","start":"tt-1516"},{"clip":"MF019_1971_CT_SU2011_VA_04","tag":"Noun:Alina","type":"Vocab","end":"tt-1578","start":"tt-1578"},{"clip":"MF019_1971_CT_SU2011_VA_04","tag":"Adjective:distinto","type":"Vocab","end":"tt-1163","start":"tt-1163"},{"clip":"MF019_1971_CT_SU2011_VA_04","tag":"Noun:edad","type":"Vocab","end":"tt-1080","start":"tt-1080"},{"clip":"MF019_1971_CT_SU2011_VA_04","tag":"Noun:año","type":"Vocab","end":"tt-1124","start":"tt-1124"},{"clip":"MF019_1971_CT_SU2011_VA_04","tag":"Noun:año","type":"Vocab","end":"tt-1071","start":"tt-1071"},{"clip":"MF019_1971_CT_SU2011_VA_04","tag":"Verb:hacer","type":"Vocab","end":"tt-1303","start":"tt-1303"},{"clip":"MF019_1971_CT_SU2011_VA_04","tag":"Verb:casar","type":"Vocab","end":"tt-1042","start":"tt-1042"},{"clip":"MF019_1971_CT_SU2011_VA_04","tag":"Noun:edad","type":"Vocab","end":"tt-1153","start":"tt-1153"},{"clip":"MF019_1971_CT_SU2011_VA_04","tag":"Verb:decir","type":"Vocab","end":"tt-1656","start":"tt-1656"},{"clip":"MF019_1971_CT_SU2011_VA_04","tag":"Verb:ser","type":"Vocab","end":"tt-1508","start":"tt-1508"},{"clip":"MF019_1971_CT_SU2011_VA_04","tag":"Verb:haber","type":"Vocab","end":"tt-1063","start":"tt-1063"},{"clip":"MF019_1971_CT_SU2011_VA_04","tag":"Adjective:serio","type":"Vocab","end":"tt-1484","start":"tt-1484"},{"clip":"MF019_1971_CT_SU2011_VA_04","tag":"Noun:lava","type":"Vocab","end":"tt-1048","start":"tt-1048"},{"clip":"MF019_1971_CT_SU2011_VA_04","tag":"Noun:este","type":"Vocab","end":"tt-1280","start":"tt-1280"},{"clip":"MF019_1971_CT_SU2011_VA_04","tag":"Verb:ser","type":"Vocab","end":"tt-1596","start":"tt-1596"},{"clip":"MF019_1971_CT_SU2011_VA_04","tag":"Verb:ser","type":"Vocab","end":"tt-1349","start":"tt-1349"},{"clip":"MF019_1971_CT_SU2011_VA_04","tag":"Verb:tener","type":"Vocab","end":"tt-1109","start":"tt-1109"},{"clip":"MF019_1971_CT_SU2011_VA_04","tag":"Noun:verdad","type":"Vocab","end":"tt-1364","start":"tt-1364"},{"clip":"MF019_1971_CT_SU2011_VA_04","tag":"Verb:poder","type":"Vocab","end":"tt-1385","start":"tt-1385"},{"clip":"MF019_1971_CT_SU2011_VA_04","tag":"Verb:parar","type":"Vocab","end":"tt-1342","start":"tt-1342"},{"clip":"MF019_1971_CT_SU2011_VA_04","tag":"Verb:ser","type":"Vocab","end":"tt-1485","start":"tt-1485"},{"clip":"MF019_1971_CT_SU2011_VA_04","tag":"Verb:ser","type":"Vocab","end":"tt-1691","start":"tt-1691"},{"clip":"MF019_1971_CT_SU2011_VA_04","tag":"Noun:UNK","type":"Vocab","end":"tt-1538","start":"tt-1538"},{"clip":"MF019_1971_CT_SU2011_VA_04","tag":"Verb:ser","type":"Vocab","end":"tt-1091","start":"tt-1091"},{"clip":"MF019_1971_CT_SU2011_VA_04","tag":"Verb:ser","type":"Vocab","end":"tt-1197","start":"tt-1197"},{"clip":"MF019_1971_CT_SU2011_VA_04","tag":"Adjective:grande","type":"Vocab","end":"tt-1168","start":"tt-1168"},{"clip":"MF019_1971_CT_SU2011_VA_04","tag":"Noun:americano","type":"Vocab","end":"tt-1045","start":"tt-1045"},{"clip":"MF019_1971_CT_SU2011_VA_04","tag":"Noun:Alina","type":"Vocab","end":"tt-1668","start":"tt-1668"},{"clip":"MF019_1971_CT_SU2011_VA_04","tag":"Verb:ser","type":"Vocab","end":"tt-1174","start":"tt-1174"},{"clip":"MF019_1971_CT_SU2011_VA_04","tag":"Verb:tomar","type":"Vocab","end":"tt-1641","start":"tt-1641"},{"clip":"MF019_1971_CT_SU2011_VA_04","tag":"Noun:pared","type":"Vocab","end":"tt-1553","start":"tt-1553"},{"clip":"MF019_1971_CT_SU2011_VA_04","tag":"Noun:cosa","type":"Vocab","end":"tt-1242","start":"tt-1242"},{"clip":"MF019_1971_CT_SU2011_VA_04","tag":"Verb:tener","type":"Vocab","end":"tt-1321","start":"tt-1321"},{"clip":"MF019_1971_CT_SU2011_VA_04","tag":"Verb:ser","type":"Vocab","end":"tt-1346","start":"tt-1346"},{"clip":"MF019_1971_CT_SU2011_VA_04","tag":"Verb:querer","type":"Vocab","end":"tt-1391","start":"tt-1391"},{"clip":"MF019_1971_CT_SU2011_VA_04","tag":"Verb:reír","type":"Vocab","end":"tt-1499","start":"tt-1499"},{"clip":"MF019_1971_CT_SU2011_VA_04","tag":"Verb:ser","type":"Vocab","end":"tt-1461","start":"tt-1461"},{"clip":"MF019_1971_CT_SU2011_VA_04","tag":"Noun:felicidad","type":"Vocab","end":"tt-1206","start":"tt-1206"},{"clip":"MF019_1971_CT_SU2011_VA_04","tag":"Adjective:fácil","type":"Vocab","end":"tt-1288","start":"tt-1288"},{"clip":"MF019_1971_CT_SU2011_VA_04","tag":"Noun:Austin","type":"Vocab","end":"tt-1468","start":"tt-1468"},{"clip":"MF019_1971_CT_SU2011_VA_04","tag":"Noun:cuenta","type":"Vocab","end":"tt-1643","start":"tt-1643"},{"clip":"MF019_1971_CT_SU2011_VA_04","tag":"Verb:UNK","type":"Vocab","end":"tt-1604","start":"tt-1604"},{"clip":"MF019_1971_CT_SU2011_VA_04","tag":"Noun:techo","type":"Vocab","end":"tt-1551","start":"tt-1551"},{"clip":"MF019_1971_CT_SU2011_VA_04","tag":"Noun:personalidad","type":"Vocab","end":"tt-1161","start":"tt-1161"},{"clip":"MF019_1971_CT_SU2011_VA_04","tag":"Noun:UNK","type":"Vocab","end":"tt-1267","start":"tt-1267"},{"clip":"MF019_1971_CT_SU2011_VA_04","tag":"Noun:dos","type":"Vocab","end":"tt-1345","start":"tt-1345"},{"clip":"MF019_1971_CT_SU2011_VA_04","tag":"Noun:Lucy","type":"Vocab","end":"tt-1308","start":"tt-1308"},{"clip":"MF019_1971_CT_SU2011_VA_04","tag":"Adjective:serio","type":"Vocab","end":"tt-1283","start":"tt-1283"},{"clip":"MF019_1971_CT_SU2011_VA_04","tag":"Verb:caminar","type":"Vocab","end":"tt-1620","start":"tt-1620"},{"clip":"MF019_1971_CT_SU2011_VA_04","tag":"Verb:decir","type":"Vocab","end":"tt-1530","start":"tt-1530"},{"clip":"MF019_1971_CT_SU2011_VA_04","tag":"Noun:familia","type":"Vocab","end":"tt-1515","start":"tt-1515"},{"clip":"MF019_1971_CT_SU2011_VA_04","tag":"Adjective:maternal","type":"Vocab","end":"tt-1358","start":"tt-1358"},{"clip":"MF019_1971_CT_SU2011_VA_04","tag":"Verb:tener","type":"Vocab","end":"tt-1355","start":"tt-1355"},{"clip":"MF019_1971_CT_SU2011_VA_04","tag":"Noun:UNK","type":"Vocab","end":"tt-1680","start":"tt-1680"},{"clip":"MF019_1971_CT_SU2011_VA_04","tag":"Noun:período","type":"Vocab","end":"tt-1122","start":"tt-1122"},{"clip":"MF019_1971_CT_SU2011_VA_04","tag":"Noun:madre","type":"Vocab","end":"tt-1087","start":"tt-1087"},{"clip":"MF019_1971_CT_SU2011_VA_04","tag":"Verb:ser","type":"Vocab","end":"tt-1614","start":"tt-1614"},{"clip":"MF019_1971_CT_SU2011_VA_04","tag":"Noun:llave","type":"Vocab","end":"tt-1438","start":"tt-1438"},{"clip":"MF019_1971_CT_SU2011_VA_04","tag":"Verb:secundar","type":"Vocab","end":"tt-1313","start":"tt-1313"},{"clip":"MF019_1971_CT_SU2011_VA_04","tag":"Verb:tener","type":"Vocab","end":"tt-1096","start":"tt-1096"},{"clip":"MF019_1971_CT_SU2011_VA_04","tag":"Verb:contar","type":"Vocab","end":"tt-1558","start":"tt-1558"},{"clip":"MF019_1971_CT_SU2011_VA_04","tag":"Verb:ser","type":"Vocab","end":"tt-1581","start":"tt-1581"},{"clip":"MF019_1971_CT_SU2011_VA_04","tag":"Noun:UNK","type":"Vocab","end":"tt-1049","start":"tt-1049"},{"clip":"MF019_1971_CT_SU2011_VA_04","tag":"Verb:ser","type":"Vocab","end":"tt-1588","start":"tt-1588"},{"clip":"MF019_1971_CT_SU2011_VA_04","tag":"Verb:ser","type":"Vocab","end":"tt-1379","start":"tt-1379"},{"clip":"MF019_1971_CT_SU2011_VA_04","tag":"Verb:salir","type":"Vocab","end":"tt-1386","start":"tt-1386"},{"clip":"MF019_1971_CT_SU2011_VA_04","tag":"Verb:hacer","type":"Vocab","end":"tt-1233","start":"tt-1233"},{"clip":"MF019_1971_CT_SU2011_VA_04","tag":"Verb:haber","type":"Vocab","end":"tt-1437","start":"tt-1437"},{"clip":"MF019_1971_CT_SU2011_VA_04","tag":"Verb:reír","type":"Vocab","end":"tt-1265","start":"tt-1265"},{"clip":"MF019_1971_CT_SU2011_VA_04","tag":"Verb:ser","type":"Vocab","end":"tt-1282","start":"tt-1282"},{"clip":"MF019_1971_CT_SU2011_VA_04","tag":"Verb:hacer","type":"Vocab","end":"tt-1264","start":"tt-1264"},{"clip":"MF019_1971_CT_SU2011_VA_04","tag":"Noun:Jorge","type":"Vocab","end":"tt-1368","start":"tt-1368"},{"clip":"MF019_1971_CT_SU2011_VA_04","tag":"Noun:hermano","type":"Vocab","end":"tt-1457","start":"tt-1457"},{"clip":"MF019_1971_CT_SU2011_VA_04","tag":"Adjective:serio","type":"Vocab","end":"tt-1179","start":"tt-1179"},{"clip":"MF019_1971_CT_SU2011_VA_04","tag":"Adjective:serio","type":"Vocab","end":"tt-1671","start":"tt-1671"},{"clip":"MF019_1971_CT_SU2011_VA_04","tag":"Verb:ser","type":"Vocab","end":"tt-1571","start":"tt-1571"},{"clip":"MF019_1971_CT_SU2011_VA_04","tag":"Verb:seguir","type":"Vocab","end":"tt-1626","start":"tt-1626"},{"clip":"MF019_1971_CT_SU2011_VA_04","tag":"Verb:ser","type":"Vocab","end":"tt-1279","start":"tt-1279"},{"clip":"MF019_1971_CT_SU2011_VA_04","tag":"Adjective:grande","type":"Vocab","end":"tt-1068","start":"tt-1068"},{"clip":"MF019_1971_CT_SU2011_VA_04","tag":"Adjective:serio","type":"Vocab","end":"tt-1324","start":"tt-1324"},{"clip":"MF019_1971_CT_SU2011_VA_04","tag":"Adjective:UNK","type":"Vocab","end":"tt-1462","start":"tt-1462"},{"clip":"MF019_1971_CT_SU2011_VA_04","tag":"Noun:situación","type":"Vocab","end":"tt-1524","start":"tt-1524"},{"clip":"MF019_1971_CT_SU2011_VA_04","tag":"Noun:niño","type":"Vocab","end":"tt-1382","start":"tt-1382"},{"clip":"MF019_1971_CT_SU2011_VA_04","tag":"Adjective:bueno","type":"Vocab","end":"tt-1539","start":"tt-1539"},{"clip":"MF019_1971_CT_SU2011_VA_04","tag":"Verb:seguir","type":"Vocab","end":"tt-1101","start":"tt-1101"},{"clip":"MF019_1971_CT_SU2011_VA_04","tag":"Adjective:mismo","type":"Vocab","end":"tt-1404","start":"tt-1404"}]