[{"clip":"MM014_1961_EP_SU2011_AD_10","tag":"Pron","type":"Gram","end":"tt-2286","start":"tt-2286"},{"clip":"MM014_1961_EP_SU2011_AD_10","tag":"Pron:Sujeto","type":"Gram","end":"tt-2286","start":"tt-2286"},{"clip":"MM014_1961_EP_SU2011_AD_11","tag":"Pron","type":"Gram","end":"tt-2294","start":"tt-2294"},{"clip":"MM014_1961_EP_SU2011_AD_11","tag":"Pron:Objeto","type":"Gram","end":"tt-2294","start":"tt-2294"},{"clip":"MM014_1961_EP_SU2011_AD_11","tag":"Prep","type":"Gram","end":"tt-2297","start":"tt-2297"},{"clip":"MM014_1961_EP_SU2011_AD_11","tag":"Prep","type":"Gram","end":"tt-2298","start":"tt-2298"},{"clip":"MM014_1961_EP_SU2011_AD_11","tag":"Pron","type":"Gram","end":"tt-2299","start":"tt-2299"},{"clip":"MM014_1961_EP_SU2011_AD_11","tag":"Pron:Sujeto","type":"Gram","end":"tt-2299","start":"tt-2299"},{"clip":"MM014_1961_EP_SU2011_AD_11","tag":"Det","type":"Gram","end":"tt-2305","start":"tt-2305"},{"clip":"MM014_1961_EP_SU2011_AD_11","tag":"Det:Art","type":"Gram","end":"tt-2305","start":"tt-2305"},{"clip":"MM014_1961_EP_SU2011_AD_11","tag":"Prep","type":"Gram","end":"tt-2307","start":"tt-2307"},{"clip":"MM014_1961_EP_SU2011_AD_11","tag":"Prep","type":"Gram","end":"tt-2312","start":"tt-2312"},{"clip":"MM014_1961_EP_SU2011_AD_11","tag":"Det","type":"Gram","end":"tt-2315","start":"tt-2315"},{"clip":"MM014_1961_EP_SU2011_AD_11","tag":"Det:Art","type":"Gram","end":"tt-2315","start":"tt-2315"},{"clip":"MM014_1961_EP_SU2011_AD_11","tag":"Prep","type":"Gram","end":"tt-2318","start":"tt-2318"},{"clip":"MM014_1961_EP_SU2011_AD_11","tag":"Prep","type":"Gram","end":"tt-2321","start":"tt-2321"},{"clip":"MM014_1961_EP_SU2011_AD_11","tag":"Prep","type":"Gram","end":"tt-2322","start":"tt-2322"},{"clip":"MM014_1961_EP_SU2011_AD_11","tag":"Indefinido","type":"Gram","end":"tt-2326","start":"tt-2326"},{"clip":"MM014_1961_EP_SU2011_AD_11","tag":"Prep","type":"Gram","end":"tt-2343","start":"tt-2343"},{"clip":"MM014_1961_EP_SU2011_AD_11","tag":"Det","type":"Gram","end":"tt-2344","start":"tt-2344"},{"clip":"MM014_1961_EP_SU2011_AD_11","tag":"Det:Art","type":"Gram","end":"tt-2344","start":"tt-2344"},{"clip":"MM014_1961_EP_SU2011_AD_11","tag":"Haber","type":"Gram","end":"tt-2350","start":"tt-2350"},{"clip":"MM014_1961_EP_SU2011_AD_11","tag":"Haber:Exist","type":"Gram","end":"tt-2350","start":"tt-2350"},{"clip":"MM014_1961_EP_SU2011_AD_11","tag":"Det","type":"Gram","end":"tt-2354","start":"tt-2354"},{"clip":"MM014_1961_EP_SU2011_AD_11","tag":"Det:Art","type":"Gram","end":"tt-2354","start":"tt-2354"},{"clip":"MM014_1961_EP_SU2011_AD_11","tag":"Pron","type":"Gram","end":"tt-2357","start":"tt-2357"},{"clip":"MM014_1961_EP_SU2011_AD_11","tag":"Pron:Objeto","type":"Gram","end":"tt-2357","start":"tt-2357"},{"clip":"MM014_1961_EP_SU2011_AD_11","tag":"Pron","type":"Gram","end":"tt-2360","start":"tt-2360"},{"clip":"MM014_1961_EP_SU2011_AD_11","tag":"Pron:Sujeto","type":"Gram","end":"tt-2360","start":"tt-2360"},{"clip":"MM014_1961_EP_SU2011_AD_11","tag":"Prep","type":"Gram","end":"tt-2364","start":"tt-2364"},{"clip":"MM014_1961_EP_SU2011_AD_11","tag":"Pron","type":"Gram","end":"tt-2370","start":"tt-2370"},{"clip":"MM014_1961_EP_SU2011_AD_11","tag":"Pron:Objeto","type":"Gram","end":"tt-2370","start":"tt-2370"},{"clip":"MM014_1961_EP_SU2011_AD_11","tag":"MSub","type":"Gram","end":"tt-2375","start":"tt-2375"},{"clip":"MM014_1961_EP_SU2011_AD_11","tag":"MSub:Pret","type":"Gram","end":"tt-2375","start":"tt-2375"},{"clip":"MM014_1961_EP_SU2011_AD_11","tag":"SerEstar","type":"Gram","end":"tt-2376","start":"tt-2376"},{"clip":"MM014_1961_EP_SU2011_AD_11","tag":"SerEstar:Ser","type":"Gram","end":"tt-2376","start":"tt-2376"},{"clip":"MM014_1961_EP_SU2011_AD_11","tag":"SerEstar","type":"Gram","end":"tt-2378","start":"tt-2378"},{"clip":"MM014_1961_EP_SU2011_AD_11","tag":"SerEstar:Ser","type":"Gram","end":"tt-2378","start":"tt-2378"},{"clip":"MM014_1961_EP_SU2011_AD_11","tag":"SerEstar","type":"Gram","end":"tt-2391","start":"tt-2391"},{"clip":"MM014_1961_EP_SU2011_AD_11","tag":"SerEstar:Ser","type":"Gram","end":"tt-2391","start":"tt-2391"},{"clip":"MM014_1961_EP_SU2011_AD_11","tag":"Det","type":"Gram","end":"tt-2392","start":"tt-2392"},{"clip":"MM014_1961_EP_SU2011_AD_11","tag":"Det:Art","type":"Gram","end":"tt-2392","start":"tt-2392"},{"clip":"MM014_1961_EP_SU2011_AD_11","tag":"Prep","type":"Gram","end":"tt-2396","start":"tt-2396"},{"clip":"MM014_1961_EP_SU2011_AD_11","tag":"MarcadoresDisc","type":"Prag","end":"tt-2405","start":"tt-2405"},{"clip":"MM014_1961_EP_SU2011_AD_11","tag":"MarcadoresDisc:Revision","type":"Prag","end":"tt-2405","start":"tt-2405"},{"clip":"MM014_1961_EP_SU2011_AD_11","tag":"Prep","type":"Gram","end":"tt-2407","start":"tt-2407"},{"clip":"MM014_1961_EP_SU2011_AD_11","tag":"Pron","type":"Gram","end":"tt-2408","start":"tt-2408"},{"clip":"MM014_1961_EP_SU2011_AD_11","tag":"Pron:Sujeto","type":"Gram","end":"tt-2408","start":"tt-2408"},{"clip":"MM014_1961_EP_SU2011_AD_11","tag":"SerEstar","type":"Gram","end":"tt-2409","start":"tt-2409"},{"clip":"MM014_1961_EP_SU2011_AD_11","tag":"SerEstar:Ser","type":"Gram","end":"tt-2409","start":"tt-2409"},{"clip":"MM014_1961_EP_SU2011_AD_11","tag":"SerEstar","type":"Gram","end":"tt-2412","start":"tt-2412"},{"clip":"MM014_1961_EP_SU2011_AD_11","tag":"SerEstar:Ser","type":"Gram","end":"tt-2412","start":"tt-2412"},{"clip":"MM014_1961_EP_SU2011_AD_11","tag":"Det","type":"Gram","end":"tt-2413","start":"tt-2413"},{"clip":"MM014_1961_EP_SU2011_AD_11","tag":"Det:Art","type":"Gram","end":"tt-2413","start":"tt-2413"},{"clip":"MM014_1961_EP_SU2011_AD_11","tag":"Prep","type":"Gram","end":"tt-2415","start":"tt-2415"},{"clip":"MM014_1961_EP_SU2011_AD_11","tag":"Pron","type":"Gram","end":"tt-2421","start":"tt-2421"},{"clip":"MM014_1961_EP_SU2011_AD_11","tag":"Pron:Objeto","type":"Gram","end":"tt-2421","start":"tt-2421"},{"clip":"MM014_1961_EP_SU2011_AD_11","tag":"Pron","type":"Gram","end":"tt-2434","start":"tt-2434"},{"clip":"MM014_1961_EP_SU2011_AD_11","tag":"Pron:Sujeto","type":"Gram","end":"tt-2434","start":"tt-2434"},{"clip":"MM014_1961_EP_SU2011_AD_11","tag":"Imperf","type":"Gram","end":"tt-2437","start":"tt-2437"},{"clip":"MM014_1961_EP_SU2011_AD_11","tag":"Prep","type":"Gram","end":"tt-2438","start":"tt-2438"},{"clip":"MM014_1961_EP_SU2011_AD_11","tag":"SerEstar","type":"Gram","end":"tt-2441","start":"tt-2441"},{"clip":"MM014_1961_EP_SU2011_AD_11","tag":"SerEstar:Ser","type":"Gram","end":"tt-2441","start":"tt-2441"},{"clip":"MM014_1961_EP_SU2011_AD_11","tag":"Pron","type":"Gram","end":"tt-2445","start":"tt-2445"},{"clip":"MM014_1961_EP_SU2011_AD_11","tag":"Pron:Sujeto","type":"Gram","end":"tt-2445","start":"tt-2445"},{"clip":"MM014_1961_EP_SU2011_AD_11","tag":"Pron","type":"Gram","end":"tt-2446","start":"tt-2446"},{"clip":"MM014_1961_EP_SU2011_AD_11","tag":"Pron:Objeto","type":"Gram","end":"tt-2446","start":"tt-2446"},{"clip":"MM014_1961_EP_SU2011_AD_11","tag":"Det","type":"Gram","end":"tt-2448","start":"tt-2448"},{"clip":"MM014_1961_EP_SU2011_AD_11","tag":"Det:Art","type":"Gram","end":"tt-2448","start":"tt-2448"},{"clip":"MM014_1961_EP_SU2011_AD_11","tag":"Prep","type":"Gram","end":"tt-2450","start":"tt-2450"},{"clip":"MM014_1961_EP_SU2011_AD_11","tag":"SerEstar","type":"Gram","end":"tt-2452","start":"tt-2452"},{"clip":"MM014_1961_EP_SU2011_AD_11","tag":"SerEstar:Ser","type":"Gram","end":"tt-2452","start":"tt-2452"},{"clip":"MM014_1961_EP_SU2011_AD_11","tag":"Pron","type":"Gram","end":"tt-2457","start":"tt-2457"},{"clip":"MM014_1961_EP_SU2011_AD_11","tag":"Pron:Sujeto","type":"Gram","end":"tt-2457","start":"tt-2457"},{"clip":"MM014_1961_EP_SU2011_AD_11","tag":"Pron","type":"Gram","end":"tt-2458","start":"tt-2458"},{"clip":"MM014_1961_EP_SU2011_AD_11","tag":"Pron:Objeto","type":"Gram","end":"tt-2458","start":"tt-2458"},{"clip":"MM014_1961_EP_SU2011_AD_11","tag":"PerfPerif","type":"Gram","end":"tt-2337","start":"tt-2336"},{"clip":"MM014_1961_EP_SU2011_AD_11","tag":"PerfPerif","type":"Gram","end":"tt-2353","start":"tt-2352"},{"clip":"MM014_1961_EP_SU2011_AD_11","tag":"PerfPerif","type":"Gram","end":"tt-2359","start":"tt-2358"},{"clip":"MM014_1961_EP_SU2011_AD_11","tag":"Gustar","type":"Gram","end":"tt-2371","start":"tt-2370"},{"clip":"MM014_1961_EP_SU2011_AD_11","tag":"Gustar:Propios","type":"Gram","end":"tt-2371","start":"tt-2370"},{"clip":"MM014_1961_EP_SU2011_AD_11","tag":"PerfPerif","type":"Gram","end":"tt-2402","start":"tt-2401"},{"clip":"MM014_1961_EP_SU2011_AD_11","tag":"PerfPerif","type":"Gram","end":"tt-2412","start":"tt-2411"},{"clip":"MM014_1961_EP_SU2011_AD_11","tag":"PerfPerif","type":"Gram","end":"tt-2423","start":"tt-2422"},{"clip":"MM014_1961_EP_SU2011_AD_11","tag":"Verb:ser","type":"Vocab","end":"tt-2391","start":"tt-2391"},{"clip":"MM014_1961_EP_SU2011_AD_11","tag":"Verb:poder","type":"Vocab","end":"tt-2295","start":"tt-2295"},{"clip":"MM014_1961_EP_SU2011_AD_11","tag":"Noun:problema","type":"Vocab","end":"tt-2338","start":"tt-2338"},{"clip":"MM014_1961_EP_SU2011_AD_11","tag":"Noun:hijo","type":"Vocab","end":"tt-2290","start":"tt-2290"},{"clip":"MM014_1961_EP_SU2011_AD_11","tag":"Verb:seguir","type":"Vocab","end":"tt-2383","start":"tt-2383"},{"clip":"MM014_1961_EP_SU2011_AD_11","tag":"Noun:logro","type":"Vocab","end":"tt-2462","start":"tt-2462"},{"clip":"MM014_1961_EP_SU2011_AD_11","tag":"Verb:UNK","type":"Vocab","end":"tt-2359","start":"tt-2359"},{"clip":"MM014_1961_EP_SU2011_AD_11","tag":"Noun:momento","type":"Vocab","end":"tt-2393","start":"tt-2393"},{"clip":"MM014_1961_EP_SU2011_AD_11","tag":"Verb:inculcar","type":"Vocab","end":"tt-2365","start":"tt-2365"},{"clip":"MM014_1961_EP_SU2011_AD_11","tag":"Verb:tener","type":"Vocab","end":"tt-2291","start":"tt-2291"},{"clip":"MM014_1961_EP_SU2011_AD_11","tag":"Verb:contar","type":"Vocab","end":"tt-2296","start":"tt-2296"},{"clip":"MM014_1961_EP_SU2011_AD_11","tag":"Verb:haber","type":"Vocab","end":"tt-2358","start":"tt-2358"},{"clip":"MM014_1961_EP_SU2011_AD_11","tag":"Verb:tratar","type":"Vocab","end":"tt-2437","start":"tt-2437"},{"clip":"MM014_1961_EP_SU2011_AD_11","tag":"Verb:esperar","type":"Vocab","end":"tt-2340","start":"tt-2340"},{"clip":"MM014_1961_EP_SU2011_AD_11","tag":"Noun:UNK","type":"Vocab","end":"tt-2416","start":"tt-2416"},{"clip":"MM014_1961_EP_SU2011_AD_11","tag":"Verb:tener","type":"Vocab","end":"tt-2342","start":"tt-2342"},{"clip":"MM014_1961_EP_SU2011_AD_11","tag":"Noun:vida","type":"Vocab","end":"tt-2398","start":"tt-2398"},{"clip":"MM014_1961_EP_SU2011_AD_11","tag":"Noun:estudiante","type":"Vocab","end":"tt-2329","start":"tt-2329"},{"clip":"MM014_1961_EP_SU2011_AD_11","tag":"Noun:hijo","type":"Vocab","end":"tt-2303","start":"tt-2303"},{"clip":"MM014_1961_EP_SU2011_AD_11","tag":"Verb:ser","type":"Vocab","end":"tt-2376","start":"tt-2376"},{"clip":"MM014_1961_EP_SU2011_AD_11","tag":"Adjective:grande","type":"Vocab","end":"tt-2306","start":"tt-2306"},{"clip":"MM014_1961_EP_SU2011_AD_11","tag":"Verb:tener","type":"Vocab","end":"tt-2337","start":"tt-2337"},{"clip":"MM014_1961_EP_SU2011_AD_11","tag":"Adjective:bueno","type":"Vocab","end":"tt-2453","start":"tt-2453"},{"clip":"MM014_1961_EP_SU2011_AD_11","tag":"Noun:estudiante","type":"Vocab","end":"tt-2454","start":"tt-2454"},{"clip":"MM014_1961_EP_SU2011_AD_11","tag":"Verb:ser","type":"Vocab","end":"tt-2441","start":"tt-2441"},{"clip":"MM014_1961_EP_SU2011_AD_11","tag":"Noun:hijo","type":"Vocab","end":"tt-2333","start":"tt-2333"},{"clip":"MM014_1961_EP_SU2011_AD_11","tag":"Verb:tener","type":"Vocab","end":"tt-2301","start":"tt-2301"},{"clip":"MM014_1961_EP_SU2011_AD_11","tag":"Verb:gustar","type":"Vocab","end":"tt-2371","start":"tt-2371"},{"clip":"MM014_1961_EP_SU2011_AD_11","tag":"Noun:estudiante","type":"Vocab","end":"tt-2429","start":"tt-2429"},{"clip":"MM014_1961_EP_SU2011_AD_11","tag":"Noun:satisfacción","type":"Vocab","end":"tt-2449","start":"tt-2449"},{"clip":"MM014_1961_EP_SU2011_AD_11","tag":"Verb:ser","type":"Vocab","end":"tt-2409","start":"tt-2409"},{"clip":"MM014_1961_EP_SU2011_AD_11","tag":"Verb:ser","type":"Vocab","end":"tt-2452","start":"tt-2452"},{"clip":"MM014_1961_EP_SU2011_AD_11","tag":"Verb:haber","type":"Vocab","end":"tt-2336","start":"tt-2336"},{"clip":"MM014_1961_EP_SU2011_AD_11","tag":"Noun:raíz","type":"Vocab","end":"tt-2385","start":"tt-2385"},{"clip":"MM014_1961_EP_SU2011_AD_11","tag":"Verb:haber","type":"Vocab","end":"tt-2352","start":"tt-2352"},{"clip":"MM014_1961_EP_SU2011_AD_11","tag":"Noun:dios","type":"Vocab","end":"tt-2323","start":"tt-2323"},{"clip":"MM014_1961_EP_SU2011_AD_11","tag":"Verb:salir","type":"Vocab","end":"tt-2326","start":"tt-2326"},{"clip":"MM014_1961_EP_SU2011_AD_11","tag":"Noun:valor","type":"Vocab","end":"tt-2355","start":"tt-2355"},{"clip":"MM014_1961_EP_SU2011_AD_11","tag":"Noun:eh","type":"Vocab","end":"tt-2435","start":"tt-2435"},{"clip":"MM014_1961_EP_SU2011_AD_11","tag":"Adjective:bueno","type":"Vocab","end":"tt-2442","start":"tt-2442"},{"clip":"MM014_1961_EP_SU2011_AD_11","tag":"Verb:ser","type":"Vocab","end":"tt-2378","start":"tt-2378"},{"clip":"MM014_1961_EP_SU2011_AD_11","tag":"Noun:UNK","type":"Vocab","end":"tt-2368","start":"tt-2368"},{"clip":"MM014_1961_EP_SU2011_AD_11","tag":"Verb:dar","type":"Vocab","end":"tt-2423","start":"tt-2423"},{"clip":"MM014_1961_EP_SU2011_AD_11","tag":"Noun:UNK","type":"Vocab","end":"tt-2414","start":"tt-2414"},{"clip":"MM014_1961_EP_SU2011_AD_11","tag":"Noun:futuro","type":"Vocab","end":"tt-2345","start":"tt-2345"},{"clip":"MM014_1961_EP_SU2011_AD_11","tag":"Verb:haber","type":"Vocab","end":"tt-2422","start":"tt-2422"},{"clip":"MM014_1961_EP_SU2011_AD_11","tag":"Noun:satisfacción","type":"Vocab","end":"tt-2425","start":"tt-2425"},{"clip":"MM014_1961_EP_SU2011_AD_11","tag":"Verb:llevar","type":"Vocab","end":"tt-2353","start":"tt-2353"},{"clip":"MM014_1961_EP_SU2011_AD_11","tag":"Verb:seguir","type":"Vocab","end":"tt-2375","start":"tt-2375"},{"clip":"MM014_1961_EP_SU2011_AD_11","tag":"Adjective:bueno","type":"Vocab","end":"tt-2332","start":"tt-2332"},{"clip":"MM014_1961_EP_SU2011_AD_11","tag":"Verb:tratar","type":"Vocab","end":"tt-2363","start":"tt-2363"},{"clip":"MM014_1961_EP_SU2011_AD_11","tag":"Verb:dar","type":"Vocab","end":"tt-2447","start":"tt-2447"},{"clip":"MM014_1961_EP_SU2011_AD_11","tag":"Verb:tener","type":"Vocab","end":"tt-2402","start":"tt-2402"},{"clip":"MM014_1961_EP_SU2011_AD_11","tag":"Noun:UNK","type":"Vocab","end":"tt-2289","start":"tt-2289"},{"clip":"MM014_1961_EP_SU2011_AD_11","tag":"Verb:haber","type":"Vocab","end":"tt-2411","start":"tt-2411"},{"clip":"MM014_1961_EP_SU2011_AD_11","tag":"Noun:hijo","type":"Vocab","end":"tt-2417","start":"tt-2417"},{"clip":"MM014_1961_EP_SU2011_AD_11","tag":"Adjective:bueno","type":"Vocab","end":"tt-2428","start":"tt-2428"},{"clip":"MM014_1961_EP_SU2011_AD_11","tag":"Noun:estudiante","type":"Vocab","end":"tt-2443","start":"tt-2443"},{"clip":"MM014_1961_EP_SU2011_AD_11","tag":"Verb:ser","type":"Vocab","end":"tt-2412","start":"tt-2412"},{"clip":"MM014_1961_EP_SU2011_AD_11","tag":"Verb:haber","type":"Vocab","end":"tt-2350","start":"tt-2350"},{"clip":"MM014_1961_EP_SU2011_AD_11","tag":"Noun:UNK","type":"Vocab","end":"tt-2311","start":"tt-2311"},{"clip":"MM014_1961_EP_SU2011_AD_11","tag":"Adjective:bueno","type":"Vocab","end":"tt-2328","start":"tt-2328"},{"clip":"MM014_1961_EP_SU2011_AD_11","tag":"Verb:sobresalir","type":"Vocab","end":"tt-2439","start":"tt-2439"},{"clip":"MM014_1961_EP_SU2011_AD_11","tag":"Adjective:pequeño","type":"Vocab","end":"tt-2317","start":"tt-2317"},{"clip":"MM014_1961_EP_SU2011_AD_11","tag":"Verb:haber","type":"Vocab","end":"tt-2401","start":"tt-2401"},{"clip":"MM014_1961_EP_SU2011_AD_11","tag":"Adjective:feliz","type":"Vocab","end":"tt-2395","start":"tt-2395"}]